{"config":{"output_file":null,"full_docs":false,"pub_only":false,"reachable_only":false,"distro_crate":false,"signatures":false,"borrow_data":false},"version":"0.19.0","compilation":{"directory":"e:\\Git\\Rust-Learning\\chapter10\\csv_challenge","program":"C:\\Users\\Pan\\.rustup\\toolchains\\stable-x86_64-pc-windows-msvc\\bin\\rls.exe","arguments":[],"output":"e:\\Git\\Rust-Learning\\chapter10\\csv_challenge\\target\\rls\\debug\\deps\\libcsv_challenge-b94b54be5f4a3574.rmeta"},"prelude":{"crate_id":{"name":"csv_challenge","disambiguator":[17827765997137527443,7609182771897445203]},"crate_root":"src","external_crates":[{"file_name":"e:\\Git\\Rust-Learning\\chapter10\\csv_challenge\\src\\main.rs","num":1,"id":{"name":"std","disambiguator":[45344308337484766,904807583985397655]}},{"file_name":"e:\\Git\\Rust-Learning\\chapter10\\csv_challenge\\src\\main.rs","num":2,"id":{"name":"core","disambiguator":[17608585110195136257,12532935013018738971]}},{"file_name":"e:\\Git\\Rust-Learning\\chapter10\\csv_challenge\\src\\main.rs","num":3,"id":{"name":"compiler_builtins","disambiguator":[10644633998059158352,10345665241509147306]}},{"file_name":"e:\\Git\\Rust-Learning\\chapter10\\csv_challenge\\src\\main.rs","num":4,"id":{"name":"rustc_std_workspace_core","disambiguator":[18212625787733517551,4937265065110821766]}},{"file_name":"e:\\Git\\Rust-Learning\\chapter10\\csv_challenge\\src\\main.rs","num":5,"id":{"name":"alloc","disambiguator":[2699922135837212616,11588109643627721037]}},{"file_name":"e:\\Git\\Rust-Learning\\chapter10\\csv_challenge\\src\\main.rs","num":6,"id":{"name":"libc","disambiguator":[16653465091603201180,18239440457404116996]}},{"file_name":"e:\\Git\\Rust-Learning\\chapter10\\csv_challenge\\src\\main.rs","num":7,"id":{"name":"unwind","disambiguator":[3073254730555026972,7758270140448631200]}},{"file_name":"e:\\Git\\Rust-Learning\\chapter10\\csv_challenge\\src\\main.rs","num":8,"id":{"name":"cfg_if","disambiguator":[13759999943095835806,4978516890064261122]}},{"file_name":"e:\\Git\\Rust-Learning\\chapter10\\csv_challenge\\src\\main.rs","num":9,"id":{"name":"hashbrown","disambiguator":[4575299228079760236,9361028770882531394]}},{"file_name":"e:\\Git\\Rust-Learning\\chapter10\\csv_challenge\\src\\main.rs","num":10,"id":{"name":"rustc_std_workspace_alloc","disambiguator":[10307147502021998988,15592389341950453369]}},{"file_name":"e:\\Git\\Rust-Learning\\chapter10\\csv_challenge\\src\\main.rs","num":11,"id":{"name":"rustc_demangle","disambiguator":[2670035867216739096,10315597156951015330]}},{"file_name":"e:\\Git\\Rust-Learning\\chapter10\\csv_challenge\\src\\main.rs","num":12,"id":{"name":"panic_unwind","disambiguator":[7309248630993686720,3186694738066578297]}},{"file_name":"e:\\Git\\Rust-Learning\\chapter10\\csv_challenge\\src\\main.rs","num":13,"id":{"name":"structopt","disambiguator":[14228765194081990733,5612216848854827255]}},{"file_name":"e:\\Git\\Rust-Learning\\chapter10\\csv_challenge\\src\\main.rs","num":14,"id":{"name":"clap","disambiguator":[13856399692545928350,12216083355320903317]}},{"file_name":"e:\\Git\\Rust-Learning\\chapter10\\csv_challenge\\src\\main.rs","num":15,"id":{"name":"atty","disambiguator":[9145634387548137701,10001166891196703502]}},{"file_name":"e:\\Git\\Rust-Learning\\chapter10\\csv_challenge\\src\\main.rs","num":16,"id":{"name":"winapi","disambiguator":[5935331099054663332,9435458827718120420]}},{"file_name":"e:\\Git\\Rust-Learning\\chapter10\\csv_challenge\\src\\main.rs","num":17,"id":{"name":"bitflags","disambiguator":[3603656934595766671,6397557864440674385]}},{"file_name":"e:\\Git\\Rust-Learning\\chapter10\\csv_challenge\\src\\main.rs","num":18,"id":{"name":"strsim","disambiguator":[11884319185844269032,14334940939019026352]}},{"file_name":"e:\\Git\\Rust-Learning\\chapter10\\csv_challenge\\src\\main.rs","num":19,"id":{"name":"textwrap","disambiguator":[11991496432625367495,16525833189914445119]}},{"file_name":"e:\\Git\\Rust-Learning\\chapter10\\csv_challenge\\src\\main.rs","num":20,"id":{"name":"unicode_width","disambiguator":[12229027184459297582,14033908656626698582]}},{"file_name":"e:\\Git\\Rust-Learning\\chapter10\\csv_challenge\\src\\main.rs","num":21,"id":{"name":"vec_map","disambiguator":[4761265904690810581,3174690877624574062]}},{"file_name":"e:\\Git\\Rust-Learning\\chapter10\\csv_challenge\\src\\opt.rs","num":22,"id":{"name":"structopt_derive","disambiguator":[5581260679181686593,13036062233028652919]}}],"span":{"file_name":"src\\main.rs","byte_start":0,"byte_end":1075,"line_start":1,"line_end":42,"column_start":1,"column_end":2}},"imports":[{"kind":"Use","ref_id":{"krate":13,"index":9},"span":{"file_name":"src\\main.rs","byte_start":15,"byte_end":24,"line_start":1,"line_end":1,"column_start":16,"column_end":25},"alias_span":null,"name":"StructOpt","value":"","parent":{"krate":0,"index":0}},{"kind":"Use","ref_id":{"krate":22,"index":99},"span":{"file_name":"src\\main.rs","byte_start":15,"byte_end":24,"line_start":1,"line_end":1,"column_start":16,"column_end":25},"alias_span":null,"name":"StructOpt","value":"","parent":{"krate":0,"index":3}},{"kind":"GlobUse","ref_id":null,"span":{"file_name":"src\\opt.rs","byte_start":1099,"byte_end":1100,"line_start":1,"line_end":1,"column_start":23,"column_end":24},"alias_span":null,"name":"*","value":"StructOpt","parent":{"krate":0,"index":4}},{"kind":"Use","ref_id":{"krate":0,"index":45},"span":{"file_name":"src\\main.rs","byte_start":44,"byte_end":47,"line_start":3,"line_end":3,"column_start":10,"column_end":13},"alias_span":null,"name":"Opt","value":"","parent":{"krate":0,"index":0}},{"kind":"Use","ref_id":{"krate":1,"index":2354},"span":{"file_name":"src\\err.rs","byte_start":1508,"byte_end":1510,"line_start":1,"line_end":1,"column_start":10,"column_end":12},"alias_span":null,"name":"io","value":"","parent":{"krate":0,"index":7}},{"kind":"Use","ref_id":{"krate":0,"index":78},"span":{"file_name":"src\\core\\read.rs","byte_start":2043,"byte_end":2048,"line_start":7,"line_end":7,"column_start":13,"column_end":18},"alias_span":null,"name":"Error","value":"","parent":{"krate":0,"index":14}},{"kind":"Use","ref_id":{"krate":1,"index":7320},"span":{"file_name":"src\\core\\read.rs","byte_start":2049,"byte_end":2056,"line_start":7,"line_end":7,"column_start":19,"column_end":26},"alias_span":null,"name":"PathBuf","value":"","parent":{"krate":0,"index":14}},{"kind":"Use","ref_id":{"krate":1,"index":2193},"span":{"file_name":"src\\core\\read.rs","byte_start":2057,"byte_end":2061,"line_start":7,"line_end":7,"column_start":27,"column_end":31},"alias_span":null,"name":"File","value":"","parent":{"krate":0,"index":14}},{"kind":"Use","ref_id":{"krate":1,"index":2993},"span":{"file_name":"src\\core\\read.rs","byte_start":2062,"byte_end":2066,"line_start":7,"line_end":7,"column_start":32,"column_end":36},"alias_span":null,"name":"Read","value":"","parent":{"krate":0,"index":14}},{"kind":"Use","ref_id":{"krate":1,"index":3052},"span":{"file_name":"src\\core\\read.rs","byte_start":2067,"byte_end":2072,"line_start":7,"line_end":7,"column_start":37,"column_end":42},"alias_span":null,"name":"Write","value":"","parent":{"krate":0,"index":14}},{"kind":"GlobUse","ref_id":null,"span":{"file_name":"src\\core\\write.rs","byte_start":2812,"byte_end":2813,"line_start":1,"line_end":1,"column_start":12,"column_end":13},"alias_span":null,"name":"*","value":"Error","parent":{"krate":0,"index":26}},{"kind":"Use","ref_id":{"krate":0,"index":78},"span":{"file_name":"src\\core.rs","byte_start":1854,"byte_end":1859,"line_start":3,"line_end":3,"column_start":17,"column_end":22},"alias_span":null,"name":"Error","value":"","parent":{"krate":0,"index":13}},{"kind":"Use","ref_id":{"krate":1,"index":7320},"span":{"file_name":"src\\core.rs","byte_start":1882,"byte_end":1889,"line_start":5,"line_end":5,"column_start":11,"column_end":18},"alias_span":null,"name":"PathBuf","value":"","parent":{"krate":0,"index":13}},{"kind":"Use","ref_id":{"krate":1,"index":2193},"span":{"file_name":"src\\core.rs","byte_start":1899,"byte_end":1903,"line_start":6,"line_end":6,"column_start":9,"column_end":13},"alias_span":null,"name":"File","value":"","parent":{"krate":0,"index":13}},{"kind":"Use","ref_id":{"krate":1,"index":2993},"span":{"file_name":"src\\core.rs","byte_start":1914,"byte_end":1918,"line_start":7,"line_end":7,"column_start":10,"column_end":14},"alias_span":null,"name":"Read","value":"","parent":{"krate":0,"index":13}},{"kind":"Use","ref_id":{"krate":1,"index":3052},"span":{"file_name":"src\\core.rs","byte_start":1919,"byte_end":1924,"line_start":7,"line_end":7,"column_start":15,"column_end":20},"alias_span":null,"name":"Write","value":"","parent":{"krate":0,"index":13}},{"kind":"Use","ref_id":{"krate":0,"index":21},"span":{"file_name":"src\\main.rs","byte_start":143,"byte_end":151,"line_start":8,"line_end":8,"column_start":12,"column_end":20},"alias_span":null,"name":"load_csv","value":"","parent":{"krate":0,"index":0}},{"kind":"Use","ref_id":{"krate":0,"index":22},"span":{"file_name":"src\\main.rs","byte_start":152,"byte_end":161,"line_start":8,"line_end":8,"column_start":21,"column_end":30},"alias_span":null,"name":"write_csv","value":"","parent":{"krate":0,"index":0}},{"kind":"Use","ref_id":{"krate":0,"index":28},"span":{"file_name":"src\\main.rs","byte_start":175,"byte_end":189,"line_start":9,"line_end":9,"column_start":12,"column_end":26},"alias_span":null,"name":"replace_column","value":"","parent":{"krate":0,"index":0}},{"kind":"Use","ref_id":{"krate":1,"index":7320},"span":{"file_name":"src\\main.rs","byte_start":209,"byte_end":216,"line_start":11,"line_end":11,"column_start":16,"column_end":23},"alias_span":null,"name":"PathBuf","value":"","parent":{"krate":0,"index":0}},{"kind":"Use","ref_id":{"krate":1,"index":4237},"span":{"file_name":"src\\main.rs","byte_start":227,"byte_end":234,"line_start":12,"line_end":12,"column_start":10,"column_end":17},"alias_span":null,"name":"process","value":"","parent":{"krate":0,"index":0}}],"defs":[{"kind":"Mod","id":{"krate":0,"index":0},"span":{"file_name":"src\\main.rs","byte_start":0,"byte_end":1075,"line_start":1,"line_end":42,"column_start":1,"column_end":2},"name":"","qualname":"::","value":"src\\main.rs","parent":null,"children":[{"krate":0,"index":1},{"krate":0,"index":2},{"krate":0,"index":3},{"krate":0,"index":87},{"krate":0,"index":4},{"krate":0,"index":6},{"krate":0,"index":7},{"krate":0,"index":13},{"krate":0,"index":37},{"krate":0,"index":38},{"krate":0,"index":39},{"krate":0,"index":40},{"krate":0,"index":41},{"krate":0,"index":42},{"krate":0,"index":43},{"krate":0,"index":44}],"decl_id":null,"docs":"","sig":null,"attributes":[]},{"kind":"Mod","id":{"krate":0,"index":4},"span":{"file_name":"src\\opt.rs","byte_start":0,"byte_end":0,"line_start":1,"line_end":1,"column_start":1,"column_end":1},"name":"opt","qualname":"::opt","value":"src\\opt.rs","parent":null,"children":[{"krate":0,"index":5},{"krate":0,"index":45},{"krate":0,"index":52},{"krate":0,"index":61},{"krate":0,"index":50}],"decl_id":null,"docs":"","sig":null,"attributes":[]},{"kind":"Struct","id":{"krate":0,"index":45},"span":{"file_name":"src\\opt.rs","byte_start":1190,"byte_end":1193,"line_start":4,"line_end":4,"column_start":13,"column_end":16},"name":"Opt","qualname":"::opt::Opt","value":"Opt { input, column_name, replacement, output }","parent":null,"children":[{"krate":0,"index":46},{"krate":0,"index":47},{"krate":0,"index":48},{"krate":0,"index":49}],"decl_id":null,"docs":"","sig":null,"attributes":[{"value":"structopt(name = \"csv_challenge\", about = \"Usage\")","span":{"file_name":"src\\opt.rs","byte_start":1129,"byte_end":1177,"line_start":3,"line_end":3,"column_start":1,"column_end":49}}]},{"kind":"Field","id":{"krate":0,"index":46},"span":{"file_name":"src\\opt.rs","byte_start":1239,"byte_end":1244,"line_start":6,"line_end":6,"column_start":9,"column_end":14},"name":"input","qualname":"::opt::Opt::input","value":"std::string::String","parent":{"krate":0,"index":45},"children":[],"decl_id":null,"docs":"","sig":null,"attributes":[{"value":"structopt(help = \"Input file\")","span":{"file_name":"src\\opt.rs","byte_start":1199,"byte_end":1230,"line_start":5,"line_end":5,"column_start":5,"column_end":36}}]},{"kind":"Field","id":{"krate":0,"index":47},"span":{"file_name":"src\\opt.rs","byte_start":1298,"byte_end":1309,"line_start":8,"line_end":8,"column_start":9,"column_end":20},"name":"column_name","qualname":"::opt::Opt::column_name","value":"std::string::String","parent":{"krate":0,"index":45},"children":[],"decl_id":null,"docs":"","sig":null,"attributes":[{"value":"structopt(help = \"Column Name\")","span":{"file_name":"src\\opt.rs","byte_start":1257,"byte_end":1289,"line_start":7,"line_end":7,"column_start":5,"column_end":37}}]},{"kind":"Field","id":{"krate":0,"index":48},"span":{"file_name":"src\\opt.rs","byte_start":1375,"byte_end":1386,"line_start":10,"line_end":10,"column_start":9,"column_end":20},"name":"replacement","qualname":"::opt::Opt::replacement","value":"std::string::String","parent":{"krate":0,"index":45},"children":[],"decl_id":null,"docs":"","sig":null,"attributes":[{"value":"structopt(help = \"Replacement Column Name\")","span":{"file_name":"src\\opt.rs","byte_start":1322,"byte_end":1366,"line_start":9,"line_end":9,"column_start":5,"column_end":49}}]},{"kind":"Field","id":{"krate":0,"index":49},"span":{"file_name":"src\\opt.rs","byte_start":1462,"byte_end":1468,"line_start":12,"line_end":12,"column_start":9,"column_end":15},"name":"output","qualname":"::opt::Opt::output","value":"std::option::Option<std::string::String>","parent":{"krate":0,"index":45},"children":[],"decl_id":null,"docs":"","sig":null,"attributes":[{"value":"structopt(help = \"Output file,stdout if not present\")","span":{"file_name":"src\\opt.rs","byte_start":1399,"byte_end":1453,"line_start":11,"line_end":11,"column_start":5,"column_end":59}}]},{"kind":"Mod","id":{"krate":0,"index":7},"span":{"file_name":"src\\err.rs","byte_start":0,"byte_end":0,"line_start":1,"line_end":1,"column_start":1,"column_end":1},"name":"err","qualname":"::err","value":"src\\err.rs","parent":null,"children":[{"krate":0,"index":8},{"krate":0,"index":78},{"krate":0,"index":85},{"krate":0,"index":9},{"krate":0,"index":11}],"decl_id":null,"docs":"","sig":null,"attributes":[]},{"kind":"TupleVariant","id":{"krate":0,"index":79},"span":{"file_name":"src\\err.rs","byte_start":1549,"byte_end":1551,"line_start":4,"line_end":4,"column_start":5,"column_end":7},"name":"Io","qualname":"::err::Error::Io","value":"Error::Io(io::Error)","parent":{"krate":0,"index":78},"children":[],"decl_id":null,"docs":"","sig":null,"attributes":[]},{"kind":"Field","id":{"krate":0,"index":81},"span":{"file_name":"src\\err.rs","byte_start":1552,"byte_end":1561,"line_start":4,"line_end":4,"column_start":8,"column_end":17},"name":"0","qualname":"::err::Error::Io::0","value":"std::io::Error","parent":{"krate":0,"index":79},"children":[],"decl_id":null,"docs":"","sig":null,"attributes":[]},{"kind":"TupleVariant","id":{"krate":0,"index":82},"span":{"file_name":"src\\err.rs","byte_start":1568,"byte_end":1575,"line_start":5,"line_end":5,"column_start":5,"column_end":12},"name":"Program","qualname":"::err::Error::Program","value":"Error::Program(&'static str)","parent":{"krate":0,"index":78},"children":[],"decl_id":null,"docs":"","sig":null,"attributes":[]},{"kind":"Field","id":{"krate":0,"index":84},"span":{"file_name":"src\\err.rs","byte_start":1576,"byte_end":1588,"line_start":5,"line_end":5,"column_start":13,"column_end":25},"name":"0","qualname":"::err::Error::Program::0","value":"&'static str","parent":{"krate":0,"index":82},"children":[],"decl_id":null,"docs":"","sig":null,"attributes":[]},{"kind":"Enum","id":{"krate":0,"index":78},"span":{"file_name":"src\\err.rs","byte_start":1538,"byte_end":1543,"line_start":3,"line_end":3,"column_start":10,"column_end":15},"name":"Error","qualname":"::err::Error","value":"pub enum Error { Io(io::Error), Program(&'static str), }","parent":null,"children":[{"krate":0,"index":79},{"krate":0,"index":82}],"decl_id":null,"docs":"","sig":null,"attributes":[]},{"kind":"Local","id":{"krate":0,"index":2147483658},"span":{"file_name":"src\\err.rs","byte_start":1638,"byte_end":1639,"line_start":9,"line_end":9,"column_start":13,"column_end":14},"name":"e","qualname":"<Error as std::convert::From>::from::e","value":"std::io::Error","parent":null,"children":[],"decl_id":null,"docs":"","sig":null,"attributes":[]},{"kind":"Method","id":{"krate":0,"index":10},"span":{"file_name":"src\\err.rs","byte_start":1633,"byte_end":1637,"line_start":9,"line_end":9,"column_start":8,"column_end":12},"name":"from","qualname":"<Error as std::convert::From>::from","value":"fn from(io::Error) -> Error","parent":{"krate":2,"index":1889},"children":[],"decl_id":{"krate":2,"index":1891},"docs":"","sig":null,"attributes":[]},{"kind":"Local","id":{"krate":0,"index":2147483660},"span":{"file_name":"src\\err.rs","byte_start":1735,"byte_end":1736,"line_start":14,"line_end":14,"column_start":13,"column_end":14},"name":"e","qualname":"<Error as std::convert::From>::from::e","value":"&str","parent":null,"children":[],"decl_id":null,"docs":"","sig":null,"attributes":[]},{"kind":"Method","id":{"krate":0,"index":12},"span":{"file_name":"src\\err.rs","byte_start":1730,"byte_end":1734,"line_start":14,"line_end":14,"column_start":8,"column_end":12},"name":"from","qualname":"<Error as std::convert::From>::from","value":"fn from(&'static str) -> Error","parent":{"krate":2,"index":1889},"children":[],"decl_id":{"krate":2,"index":1891},"docs":"","sig":null,"attributes":[]},{"kind":"Mod","id":{"krate":0,"index":13},"span":{"file_name":"src\\core.rs","byte_start":0,"byte_end":0,"line_start":1,"line_end":1,"column_start":1,"column_end":1},"name":"core","qualname":"::core","value":"src\\core.rs","parent":null,"children":[{"krate":0,"index":14},{"krate":0,"index":26},{"krate":0,"index":30},{"krate":0,"index":31},{"krate":0,"index":32},{"krate":0,"index":33},{"krate":0,"index":34},{"krate":0,"index":35},{"krate":0,"index":36}],"decl_id":null,"docs":"","sig":null,"attributes":[]},{"kind":"Mod","id":{"krate":0,"index":14},"span":{"file_name":"src\\core\\read.rs","byte_start":0,"byte_end":0,"line_start":1,"line_end":1,"column_start":1,"column_end":1},"name":"read","qualname":"::core::read","value":"src\\core\\read.rs","parent":null,"children":[{"krate":0,"index":15},{"krate":0,"index":16},{"krate":0,"index":17},{"krate":0,"index":18},{"krate":0,"index":19},{"krate":0,"index":20},{"krate":0,"index":21},{"krate":0,"index":22},{"krate":0,"index":23},{"krate":0,"index":24},{"krate":0,"index":25}],"decl_id":null,"docs":"","sig":null,"attributes":[]},{"kind":"Local","id":{"krate":0,"index":2147483669},"span":{"file_name":"src\\core\\read.rs","byte_start":2091,"byte_end":2099,"line_start":8,"line_end":8,"column_start":17,"column_end":25},"name":"csv_file","qualname":"::core::read::load_csv::csv_file","value":"std::path::PathBuf","parent":null,"children":[],"decl_id":null,"docs":"","sig":null,"attributes":[]},{"kind":"Function","id":{"krate":0,"index":21},"span":{"file_name":"src\\core\\read.rs","byte_start":2082,"byte_end":2090,"line_start":8,"line_end":8,"column_start":8,"column_end":16},"name":"load_csv","qualname":"::core::read::load_csv","value":"pub fn load_csv(PathBuf) -> Result<String, Error>","parent":null,"children":[],"decl_id":null,"docs":"","sig":null,"attributes":[]},{"kind":"Local","id":{"krate":0,"index":1073741845},"span":{"file_name":"src\\core\\read.rs","byte_start":2140,"byte_end":2144,"line_start":9,"line_end":9,"column_start":9,"column_end":13},"name":"file","qualname":"file$HirId { owner: DefId(0:21 ~ csv_challenge[f768]::core[0]::read[0]::load_csv[0]), local_id: 2 }","value":"std::string::String","parent":null,"children":[],"decl_id":null,"docs":"","sig":null,"attributes":[]},{"kind":"Local","id":{"krate":0,"index":134217749},"span":{"file_name":"src\\core\\read.rs","byte_start":2159,"byte_end":2160,"line_start":9,"line_end":9,"column_start":28,"column_end":29},"name":"err","qualname":"err$HirId { owner: DefId(0:21 ~ csv_challenge[f768]::core[0]::read[0]::load_csv[0]), local_id: 16 }","value":"err::Error","parent":null,"children":[],"decl_id":null,"docs":"","sig":null,"attributes":[]},{"kind":"Local","id":{"krate":0,"index":3489660949},"span":{"file_name":"src\\core\\read.rs","byte_start":2145,"byte_end":2160,"line_start":9,"line_end":9,"column_start":14,"column_end":29},"name":"val","qualname":"val$HirId { owner: DefId(0:21 ~ csv_challenge[f768]::core[0]::read[0]::load_csv[0]), local_id: 11 }","value":"std::string::String","parent":null,"children":[],"decl_id":null,"docs":"","sig":null,"attributes":[]},{"kind":"Local","id":{"krate":0,"index":2147483670},"span":{"file_name":"src\\core\\read.rs","byte_start":2195,"byte_end":2203,"line_start":13,"line_end":13,"column_start":18,"column_end":26},"name":"csv_data","qualname":"::core::read::write_csv::csv_data","value":"&str","parent":null,"children":[],"decl_id":null,"docs":"","sig":null,"attributes":[]},{"kind":"Local","id":{"krate":0,"index":1073741846},"span":{"file_name":"src\\core\\read.rs","byte_start":2209,"byte_end":2217,"line_start":13,"line_end":13,"column_start":32,"column_end":40},"name":"filename","qualname":"::core::read::write_csv::filename","value":"&str","parent":null,"children":[],"decl_id":null,"docs":"","sig":null,"attributes":[]},{"kind":"Function","id":{"krate":0,"index":22},"span":{"file_name":"src\\core\\read.rs","byte_start":2185,"byte_end":2194,"line_start":13,"line_end":13,"column_start":8,"column_end":17},"name":"write_csv","qualname":"::core::read::write_csv","value":"pub fn write_csv(&str, &str) -> Result<(), Error>","parent":null,"children":[],"decl_id":null,"docs":"","sig":null,"attributes":[]},{"kind":"Local","id":{"krate":0,"index":3355443222},"span":{"file_name":"src\\core\\read.rs","byte_start":2271,"byte_end":2272,"line_start":14,"line_end":14,"column_start":29,"column_end":30},"name":"err","qualname":"err$HirId { owner: DefId(0:22 ~ csv_challenge[f768]::core[0]::read[0]::write_csv[0]), local_id: 19 }","value":"err::Error","parent":null,"children":[],"decl_id":null,"docs":"","sig":null,"attributes":[]},{"kind":"Local","id":{"krate":0,"index":1879048214},"span":{"file_name":"src\\core\\read.rs","byte_start":2247,"byte_end":2272,"line_start":14,"line_end":14,"column_start":5,"column_end":30},"name":"val","qualname":"val$HirId { owner: DefId(0:22 ~ csv_challenge[f768]::core[0]::read[0]::write_csv[0]), local_id: 14 }","value":"()","parent":null,"children":[],"decl_id":null,"docs":"","sig":null,"attributes":[]},{"kind":"Local","id":{"krate":0,"index":2147483671},"span":{"file_name":"src\\core\\read.rs","byte_start":2296,"byte_end":2300,"line_start":18,"line_end":18,"column_start":9,"column_end":13},"name":"path","qualname":"::core::read::read::path","value":"std::path::PathBuf","parent":null,"children":[],"decl_id":null,"docs":"","sig":null,"attributes":[]},{"kind":"Function","id":{"krate":0,"index":23},"span":{"file_name":"src\\core\\read.rs","byte_start":2291,"byte_end":2295,"line_start":18,"line_end":18,"column_start":4,"column_end":8},"name":"read","qualname":"::core::read::read","value":"fn read(PathBuf) -> Result<String, Error>","parent":null,"children":[],"decl_id":null,"docs":"","sig":null,"attributes":[]},{"kind":"Local","id":{"krate":0,"index":1073741847},"span":{"file_name":"src\\core\\read.rs","byte_start":2345,"byte_end":2351,"line_start":19,"line_end":19,"column_start":13,"column_end":19},"name":"buffer","qualname":"buffer$HirId { owner: DefId(0:23 ~ csv_challenge[f768]::core[0]::read[0]::read[0]), local_id: 2 }","value":"std::string::String","parent":null,"children":[],"decl_id":null,"docs":"","sig":null,"attributes":[]},{"kind":"Local","id":{"krate":0,"index":3221225495},"span":{"file_name":"src\\core\\read.rs","byte_start":2379,"byte_end":2383,"line_start":20,"line_end":20,"column_start":13,"column_end":17},"name":"file","qualname":"file$HirId { owner: DefId(0:23 ~ csv_challenge[f768]::core[0]::read[0]::read[0]), local_id: 3 }","value":"std::fs::File","parent":null,"children":[],"decl_id":null,"docs":"","sig":null,"attributes":[]},{"kind":"Local","id":{"krate":0,"index":402653207},"span":{"file_name":"src\\core\\read.rs","byte_start":2394,"byte_end":2395,"line_start":20,"line_end":20,"column_start":28,"column_end":29},"name":"err","qualname":"err$HirId { owner: DefId(0:23 ~ csv_challenge[f768]::core[0]::read[0]::read[0]), local_id: 24 }","value":"err::Error","parent":null,"children":[],"decl_id":null,"docs":"","sig":null,"attributes":[]},{"kind":"Local","id":{"krate":0,"index":3355443223},"span":{"file_name":"src\\core\\read.rs","byte_start":2384,"byte_end":2395,"line_start":20,"line_end":20,"column_start":18,"column_end":29},"name":"val","qualname":"val$HirId { owner: DefId(0:23 ~ csv_challenge[f768]::core[0]::read[0]::read[0]), local_id: 19 }","value":"std::fs::File","parent":null,"children":[],"decl_id":null,"docs":"","sig":null,"attributes":[]},{"kind":"Local","id":{"krate":0,"index":3422552087},"span":{"file_name":"src\\core\\read.rs","byte_start":2433,"byte_end":2434,"line_start":21,"line_end":21,"column_start":37,"column_end":38},"name":"err","qualname":"err$HirId { owner: DefId(0:23 ~ csv_challenge[f768]::core[0]::read[0]::read[0]), local_id: 51 }","value":"std::io::Error","parent":null,"children":[],"decl_id":null,"docs":"","sig":null,"attributes":[]},{"kind":"Local","id":{"krate":0,"index":1946157079},"span":{"file_name":"src\\core\\read.rs","byte_start":2401,"byte_end":2434,"line_start":21,"line_end":21,"column_start":5,"column_end":38},"name":"val","qualname":"val$HirId { owner: DefId(0:23 ~ csv_challenge[f768]::core[0]::read[0]::read[0]), local_id: 46 }","value":"usize","parent":null,"children":[],"decl_id":null,"docs":"","sig":null,"attributes":[]},{"kind":"Local","id":{"krate":0,"index":1912602647},"span":{"file_name":"src\\core\\read.rs","byte_start":2502,"byte_end":2503,"line_start":23,"line_end":23,"column_start":41,"column_end":42},"name":"err","qualname":"err$HirId { owner: DefId(0:23 ~ csv_challenge[f768]::core[0]::read[0]::read[0]), local_id: 78 }","value":"&str","parent":null,"children":[],"decl_id":null,"docs":"","sig":null,"attributes":[]},{"kind":"Local","id":{"krate":0,"index":2449473559},"span":{"file_name":"src\\core\\read.rs","byte_start":2477,"byte_end":2503,"line_start":23,"line_end":23,"column_start":16,"column_end":42},"name":"val","qualname":"val$HirId { owner: DefId(0:23 ~ csv_challenge[f768]::core[0]::read[0]::read[0]), local_id: 73 }","value":"std::result::Result<std::string::String, err::Error>","parent":null,"children":[],"decl_id":null,"docs":"","sig":null,"attributes":[]},{"kind":"Local","id":{"krate":0,"index":2147483672},"span":{"file_name":"src\\core\\read.rs","byte_start":2535,"byte_end":2539,"line_start":27,"line_end":27,"column_start":9,"column_end":13},"name":"path","qualname":"::core::read::open::path","value":"std::path::PathBuf","parent":null,"children":[],"decl_id":null,"docs":"","sig":null,"attributes":[]},{"kind":"Function","id":{"krate":0,"index":24},"span":{"file_name":"src\\core\\read.rs","byte_start":2530,"byte_end":2534,"line_start":27,"line_end":27,"column_start":4,"column_end":8},"name":"open","qualname":"::core::read::open","value":"fn open(PathBuf) -> Result<File, Error>","parent":null,"children":[],"decl_id":null,"docs":"","sig":null,"attributes":[]},{"kind":"Local","id":{"krate":0,"index":1073741848},"span":{"file_name":"src\\core\\read.rs","byte_start":2578,"byte_end":2582,"line_start":28,"line_end":28,"column_start":9,"column_end":13},"name":"file","qualname":"file$HirId { owner: DefId(0:24 ~ csv_challenge[f768]::core[0]::read[0]::open[0]), local_id: 2 }","value":"std::fs::File","parent":null,"children":[],"decl_id":null,"docs":"","sig":null,"attributes":[]},{"kind":"Local","id":{"krate":0,"index":1207959576},"span":{"file_name":"src\\core\\read.rs","byte_start":2599,"byte_end":2600,"line_start":28,"line_end":28,"column_start":30,"column_end":31},"name":"err","qualname":"err$HirId { owner: DefId(0:24 ~ csv_challenge[f768]::core[0]::read[0]::open[0]), local_id: 18 }","value":"std::io::Error","parent":null,"children":[],"decl_id":null,"docs":"","sig":null,"attributes":[]},{"kind":"Local","id":{"krate":0,"index":2952790040},"span":{"file_name":"src\\core\\read.rs","byte_start":2583,"byte_end":2600,"line_start":28,"line_end":28,"column_start":14,"column_end":31},"name":"val","qualname":"val$HirId { owner: DefId(0:24 ~ csv_challenge[f768]::core[0]::read[0]::open[0]), local_id: 13 }","value":"std::fs::File","parent":null,"children":[],"decl_id":null,"docs":"","sig":null,"attributes":[]},{"kind":"Local","id":{"krate":0,"index":2147483673},"span":{"file_name":"src\\core\\read.rs","byte_start":2626,"byte_end":2630,"line_start":31,"line_end":31,"column_start":10,"column_end":14},"name":"data","qualname":"::core::read::write::data","value":"&str","parent":null,"children":[],"decl_id":null,"docs":"","sig":null,"attributes":[]},{"kind":"Local","id":{"krate":0,"index":1073741849},"span":{"file_name":"src\\core\\read.rs","byte_start":2636,"byte_end":2644,"line_start":31,"line_end":31,"column_start":20,"column_end":28},"name":"filename","qualname":"::core::read::write::filename","value":"&str","parent":null,"children":[],"decl_id":null,"docs":"","sig":null,"attributes":[]},{"kind":"Function","id":{"krate":0,"index":25},"span":{"file_name":"src\\core\\read.rs","byte_start":2620,"byte_end":2625,"line_start":31,"line_end":31,"column_start":4,"column_end":9},"name":"write","qualname":"::core::read::write","value":"fn write(&str, &str) -> Result<(), Error>","parent":null,"children":[],"decl_id":null,"docs":"","sig":null,"attributes":[]},{"kind":"Local","id":{"krate":0,"index":3221225497},"span":{"file_name":"src\\core\\read.rs","byte_start":2682,"byte_end":2688,"line_start":32,"line_end":32,"column_start":13,"column_end":19},"name":"buffer","qualname":"buffer$HirId { owner: DefId(0:25 ~ csv_challenge[f768]::core[0]::read[0]::write[0]), local_id: 3 }","value":"std::fs::File","parent":null,"children":[],"decl_id":null,"docs":"","sig":null,"attributes":[]},{"kind":"Local","id":{"krate":0,"index":671088665},"span":{"file_name":"src\\core\\read.rs","byte_start":2711,"byte_end":2712,"line_start":32,"line_end":32,"column_start":42,"column_end":43},"name":"err","qualname":"err$HirId { owner: DefId(0:25 ~ csv_challenge[f768]::core[0]::read[0]::write[0]), local_id: 20 }","value":"std::io::Error","parent":null,"children":[],"decl_id":null,"docs":"","sig":null,"attributes":[]},{"kind":"Local","id":{"krate":0,"index":4026531865},"span":{"file_name":"src\\core\\read.rs","byte_start":2689,"byte_end":2712,"line_start":32,"line_end":32,"column_start":20,"column_end":43},"name":"val","qualname":"val$HirId { owner: DefId(0:25 ~ csv_challenge[f768]::core[0]::read[0]::write[0]), local_id: 15 }","value":"std::fs::File","parent":null,"children":[],"decl_id":null,"docs":"","sig":null,"attributes":[]},{"kind":"Local","id":{"krate":0,"index":201326617},"span":{"file_name":"src\\core\\read.rs","byte_start":2751,"byte_end":2752,"line_start":33,"line_end":33,"column_start":38,"column_end":39},"name":"err","qualname":"err$HirId { owner: DefId(0:25 ~ csv_challenge[f768]::core[0]::read[0]::write[0]), local_id: 48 }","value":"std::io::Error","parent":null,"children":[],"decl_id":null,"docs":"","sig":null,"attributes":[]},{"kind":"Local","id":{"krate":0,"index":3556769817},"span":{"file_name":"src\\core\\read.rs","byte_start":2718,"byte_end":2752,"line_start":33,"line_end":33,"column_start":5,"column_end":39},"name":"val","qualname":"val$HirId { owner: DefId(0:25 ~ csv_challenge[f768]::core[0]::read[0]::write[0]), local_id: 43 }","value":"()","parent":null,"children":[],"decl_id":null,"docs":"","sig":null,"attributes":[]},{"kind":"Mod","id":{"krate":0,"index":26},"span":{"file_name":"src\\core\\write.rs","byte_start":0,"byte_end":0,"line_start":1,"line_end":1,"column_start":1,"column_end":1},"name":"write","qualname":"::core::write","value":"src\\core\\write.rs","parent":null,"children":[{"krate":0,"index":27},{"krate":0,"index":28}],"decl_id":null,"docs":"","sig":null,"attributes":[]},{"kind":"Local","id":{"krate":0,"index":2147483676},"span":{"file_name":"src\\core\\write.rs","byte_start":2837,"byte_end":2841,"line_start":2,"line_end":2,"column_start":23,"column_end":27},"name":"data","qualname":"::core::write::replace_column::data","value":"std::string::String","parent":null,"children":[],"decl_id":null,"docs":"","sig":null,"attributes":[]},{"kind":"Local","id":{"krate":0,"index":1073741852},"span":{"file_name":"src\\core\\write.rs","byte_start":2849,"byte_end":2855,"line_start":2,"line_end":2,"column_start":35,"column_end":41},"name":"column","qualname":"::core::write::replace_column::column","value":"&str","parent":null,"children":[],"decl_id":null,"docs":"","sig":null,"attributes":[]},{"kind":"Local","id":{"krate":0,"index":3221225500},"span":{"file_name":"src\\core\\write.rs","byte_start":2861,"byte_end":2872,"line_start":2,"line_end":2,"column_start":47,"column_end":58},"name":"replacement","qualname":"::core::write::replace_column::replacement","value":"&str","parent":null,"children":[],"decl_id":null,"docs":"","sig":null,"attributes":[]},{"kind":"Function","id":{"krate":0,"index":28},"span":{"file_name":"src\\core\\write.rs","byte_start":2822,"byte_end":2836,"line_start":2,"line_end":2,"column_start":8,"column_end":22},"name":"replace_column","qualname":"::core::write::replace_column","value":"pub fn replace_column(String, &str, &str) -> Result<String, Error>","parent":null,"children":[],"decl_id":null,"docs":"","sig":null,"attributes":[]},{"kind":"Local","id":{"krate":0,"index":536870940},"span":{"file_name":"src\\core\\write.rs","byte_start":2914,"byte_end":2919,"line_start":3,"line_end":3,"column_start":13,"column_end":18},"name":"lines","qualname":"lines$HirId { owner: DefId(0:28 ~ csv_challenge[f768]::core[0]::write[0]::replace_column[0]), local_id: 4 }","value":"std::str::Lines","parent":null,"children":[],"decl_id":null,"docs":"","sig":null,"attributes":[]},{"kind":"Local","id":{"krate":0,"index":2684354588},"span":{"file_name":"src\\core\\write.rs","byte_start":2942,"byte_end":2949,"line_start":4,"line_end":4,"column_start":9,"column_end":16},"name":"headers","qualname":"headers$HirId { owner: DefId(0:28 ~ csv_challenge[f768]::core[0]::write[0]::replace_column[0]), local_id: 5 }","value":"&str","parent":null,"children":[],"decl_id":null,"docs":"","sig":null,"attributes":[]},{"kind":"Local","id":{"krate":0,"index":1610612764},"span":{"file_name":"src\\core\\write.rs","byte_start":2981,"byte_end":2988,"line_start":5,"line_end":5,"column_start":9,"column_end":16},"name":"columns","qualname":"columns$HirId { owner: DefId(0:28 ~ csv_challenge[f768]::core[0]::write[0]::replace_column[0]), local_id: 6 }","value":"std::vec::Vec<&str>","parent":null,"children":[],"decl_id":null,"docs":"","sig":null,"attributes":[]},{"kind":"Local","id":{"krate":0,"index":3758096412},"span":{"file_name":"src\\core\\write.rs","byte_start":3037,"byte_end":3050,"line_start":6,"line_end":6,"column_start":9,"column_end":22},"name":"column_number","qualname":"column_number$HirId { owner: DefId(0:28 ~ csv_challenge[f768]::core[0]::write[0]::replace_column[0]), local_id: 7 }","value":"std::option::Option<usize>","parent":null,"children":[],"decl_id":null,"docs":"","sig":null,"attributes":[]},{"kind":"Local","id":{"krate":0,"index":2415919132},"span":{"file_name":"src\\core\\write.rs","byte_start":3077,"byte_end":3078,"line_start":6,"line_end":6,"column_start":49,"column_end":50},"name":"e","qualname":"$HirId { owner: DefId(0:28 ~ csv_challenge[f768]::core[0]::write[0]::replace_column[0]), local_id: 61 }::e","value":"&str","parent":null,"children":[],"decl_id":null,"docs":"","sig":null,"attributes":[]},{"kind":"Local","id":{"krate":0,"index":1342177308},"span":{"file_name":"src\\core\\write.rs","byte_start":3100,"byte_end":3113,"line_start":7,"line_end":7,"column_start":9,"column_end":22},"name":"column_number","qualname":"column_number$HirId { owner: DefId(0:28 ~ csv_challenge[f768]::core[0]::write[0]::replace_column[0]), local_id: 10 }","value":"usize","parent":null,"children":[],"decl_id":null,"docs":"","sig":null,"attributes":[]},{"kind":"Local","id":{"krate":0,"index":805306396},"span":{"file_name":"src\\core\\write.rs","byte_start":3148,"byte_end":3154,"line_start":8,"line_end":8,"column_start":14,"column_end":20},"name":"column","qualname":"column$HirId { owner: DefId(0:28 ~ csv_challenge[f768]::core[0]::write[0]::replace_column[0]), local_id: 12 }","value":"usize","parent":null,"children":[],"decl_id":null,"docs":"","sig":null,"attributes":[]},{"kind":"Local","id":{"krate":0,"index":3388997660},"span":{"file_name":"src\\core\\write.rs","byte_start":3228,"byte_end":3229,"line_start":9,"line_end":9,"column_start":64,"column_end":65},"name":"err","qualname":"err$HirId { owner: DefId(0:28 ~ csv_challenge[f768]::core[0]::write[0]::replace_column[0]), local_id: 83 }","value":"&str","parent":null,"children":[],"decl_id":null,"docs":"","sig":null,"attributes":[]},{"kind":"Local","id":{"krate":0,"index":1912602652},"span":{"file_name":"src\\core\\write.rs","byte_start":3179,"byte_end":3229,"line_start":9,"line_end":9,"column_start":15,"column_end":65},"name":"val","qualname":"val$HirId { owner: DefId(0:28 ~ csv_challenge[f768]::core[0]::write[0]::replace_column[0]), local_id: 78 }","value":"usize","parent":null,"children":[],"decl_id":null,"docs":"","sig":null,"attributes":[]},{"kind":"Local","id":{"krate":0,"index":1879048220},"span":{"file_name":"src\\core\\write.rs","byte_start":3249,"byte_end":3255,"line_start":11,"line_end":11,"column_start":13,"column_end":19},"name":"result","qualname":"result$HirId { owner: DefId(0:28 ~ csv_challenge[f768]::core[0]::write[0]::replace_column[0]), local_id: 14 }","value":"std::string::String","parent":null,"children":[],"decl_id":null,"docs":"","sig":null,"attributes":[]},{"kind":"Local","id":{"krate":0,"index":3506438172},"span":{"file_name":"src\\core\\write.rs","byte_start":3376,"byte_end":3381,"line_start":14,"line_end":14,"column_start":17,"column_end":22},"name":"iter","qualname":"iter$HirId { owner: DefId(0:28 ~ csv_challenge[f768]::core[0]::write[0]::replace_column[0]), local_id: 139 }","value":"std::str::Lines","parent":null,"children":[],"decl_id":null,"docs":"","sig":null,"attributes":[]},{"kind":"Local","id":{"krate":0,"index":4261412892},"span":{"file_name":"src\\core\\write.rs","byte_start":3376,"byte_end":3381,"line_start":14,"line_end":14,"column_start":17,"column_end":22},"name":"__next","qualname":"__next$HirId { owner: DefId(0:28 ~ csv_challenge[f768]::core[0]::write[0]::replace_column[0]), local_id: 127 }","value":"&str","parent":null,"children":[],"decl_id":null,"docs":"","sig":null,"attributes":[]},{"kind":"Local","id":{"krate":0,"index":16777244},"span":{"file_name":"src\\core\\write.rs","byte_start":3368,"byte_end":3372,"line_start":14,"line_end":14,"column_start":9,"column_end":13},"name":"val","qualname":"val$HirId { owner: DefId(0:28 ~ csv_challenge[f768]::core[0]::write[0]::replace_column[0]), local_id: 128 }","value":"&str","parent":null,"children":[],"decl_id":null,"docs":"","sig":null,"attributes":[]},{"kind":"Local","id":{"krate":0,"index":4026531868},"span":{"file_name":"src\\core\\write.rs","byte_start":3368,"byte_end":3372,"line_start":14,"line_end":14,"column_start":9,"column_end":13},"name":"line","qualname":"line$HirId { owner: DefId(0:28 ~ csv_challenge[f768]::core[0]::write[0]::replace_column[0]), local_id: 15 }","value":"&str","parent":null,"children":[],"decl_id":null,"docs":"","sig":null,"attributes":[]},{"kind":"Local","id":{"krate":0,"index":134217756},"span":{"file_name":"src\\core\\write.rs","byte_start":3399,"byte_end":3406,"line_start":15,"line_end":15,"column_start":17,"column_end":24},"name":"records","qualname":"records$HirId { owner: DefId(0:28 ~ csv_challenge[f768]::core[0]::write[0]::replace_column[0]), local_id: 16 }","value":"std::vec::Vec<&str>","parent":null,"children":[],"decl_id":null,"docs":"","sig":null,"attributes":[]},{"kind":"Function","id":{"krate":0,"index":44},"span":{"file_name":"src\\main.rs","byte_start":239,"byte_end":243,"line_start":13,"line_end":13,"column_start":4,"column_end":8},"name":"main","qualname":"::main","value":"fn main()","parent":null,"children":[],"decl_id":null,"docs":"","sig":null,"attributes":[]},{"kind":"Local","id":{"krate":0,"index":2147483692},"span":{"file_name":"src\\main.rs","byte_start":256,"byte_end":259,"line_start":14,"line_end":14,"column_start":9,"column_end":12},"name":"opt","qualname":"opt$HirId { owner: DefId(0:44 ~ csv_challenge[f768]::main[0]), local_id: 1 }","value":"opt::Opt","parent":null,"children":[],"decl_id":null,"docs":"","sig":null,"attributes":[]},{"kind":"Local","id":{"krate":0,"index":1073741868},"span":{"file_name":"src\\main.rs","byte_start":286,"byte_end":294,"line_start":15,"line_end":15,"column_start":9,"column_end":17},"name":"filename","qualname":"filename$HirId { owner: DefId(0:44 ~ csv_challenge[f768]::main[0]), local_id: 2 }","value":"std::path::PathBuf","parent":null,"children":[],"decl_id":null,"docs":"","sig":null,"attributes":[]},{"kind":"Local","id":{"krate":0,"index":3221225516},"span":{"file_name":"src\\main.rs","byte_start":334,"byte_end":342,"line_start":17,"line_end":17,"column_start":9,"column_end":17},"name":"csv_data","qualname":"csv_data$HirId { owner: DefId(0:44 ~ csv_challenge[f768]::main[0]), local_id: 3 }","value":"std::string::String","parent":null,"children":[],"decl_id":null,"docs":"","sig":null,"attributes":[]},{"kind":"Local","id":{"krate":0,"index":2684354604},"span":{"file_name":"src\\main.rs","byte_start":380,"byte_end":385,"line_start":18,"line_end":18,"column_start":12,"column_end":17},"name":"fname","qualname":"fname$HirId { owner: DefId(0:44 ~ csv_challenge[f768]::main[0]), local_id: 5 }","value":"std::string::String","parent":null,"children":[],"decl_id":null,"docs":"","sig":null,"attributes":[]},{"kind":"Local","id":{"krate":0,"index":3758096428},"span":{"file_name":"src\\main.rs","byte_start":409,"byte_end":410,"line_start":19,"line_end":19,"column_start":13,"column_end":14},"name":"e","qualname":"e$HirId { owner: DefId(0:44 ~ csv_challenge[f768]::main[0]), local_id: 7 }","value":"err::Error","parent":null,"children":[],"decl_id":null,"docs":"","sig":null,"attributes":[]},{"kind":"Local","id":{"krate":0,"index":1342177324},"span":{"file_name":"src\\main.rs","byte_start":513,"byte_end":526,"line_start":24,"line_end":24,"column_start":9,"column_end":22},"name":"modified_data","qualname":"modified_data$HirId { owner: DefId(0:44 ~ csv_challenge[f768]::main[0]), local_id: 10 }","value":"std::string::String","parent":null,"children":[],"decl_id":null,"docs":"","sig":null,"attributes":[]},{"kind":"Local","id":{"krate":0,"index":805306412},"span":{"file_name":"src\\main.rs","byte_start":604,"byte_end":608,"line_start":25,"line_end":25,"column_start":12,"column_end":16},"name":"data","qualname":"data$HirId { owner: DefId(0:44 ~ csv_challenge[f768]::main[0]), local_id: 12 }","value":"std::string::String","parent":null,"children":[],"decl_id":null,"docs":"","sig":null,"attributes":[]},{"kind":"Local","id":{"krate":0,"index":1879048236},"span":{"file_name":"src\\main.rs","byte_start":629,"byte_end":630,"line_start":26,"line_end":26,"column_start":13,"column_end":14},"name":"e","qualname":"e$HirId { owner: DefId(0:44 ~ csv_challenge[f768]::main[0]), local_id: 14 }","value":"err::Error","parent":null,"children":[],"decl_id":null,"docs":"","sig":null,"attributes":[]},{"kind":"Local","id":{"krate":0,"index":2281701420},"span":{"file_name":"src\\main.rs","byte_start":733,"byte_end":744,"line_start":31,"line_end":31,"column_start":9,"column_end":20},"name":"output_file","qualname":"output_file$HirId { owner: DefId(0:44 ~ csv_challenge[f768]::main[0]), local_id: 17 }","value":"&std::string::String","parent":null,"children":[],"decl_id":null,"docs":"","sig":null,"attributes":[]},{"kind":"Local","id":{"krate":0,"index":1744830508},"span":{"file_name":"src\\main.rs","byte_start":979,"byte_end":980,"line_start":37,"line_end":37,"column_start":13,"column_end":14},"name":"e","qualname":"e$HirId { owner: DefId(0:44 ~ csv_challenge[f768]::main[0]), local_id: 22 }","value":"err::Error","parent":null,"children":[],"decl_id":null,"docs":"","sig":null,"attributes":[]}],"impls":[{"id":2,"kind":"Direct","span":{"file_name":"src\\err.rs","byte_start":1619,"byte_end":1624,"line_start":8,"line_end":8,"column_start":26,"column_end":31},"value":"","parent":null,"children":[{"krate":0,"index":10}],"docs":"","sig":null,"attributes":[]},{"id":3,"kind":"Direct","span":{"file_name":"src\\err.rs","byte_start":1716,"byte_end":1721,"line_start":13,"line_end":13,"column_start":29,"column_end":34},"value":"","parent":null,"children":[{"krate":0,"index":12}],"docs":"","sig":null,"attributes":[]}],"refs":[{"kind":"Mod","span":{"file_name":"src\\main.rs","byte_start":4,"byte_end":13,"line_start":1,"line_end":1,"column_start":5,"column_end":14},"ref_id":{"krate":13,"index":0}},{"kind":"Mod","span":{"file_name":"src\\main.rs","byte_start":30,"byte_end":33,"line_start":2,"line_end":2,"column_start":5,"column_end":8},"ref_id":{"krate":0,"index":4}},{"kind":"Mod","span":{"file_name":"src\\opt.rs","byte_start":1081,"byte_end":1097,"line_start":1,"line_end":1,"column_start":5,"column_end":21},"ref_id":{"krate":22,"index":0}},{"kind":"Type","span":{"file_name":"src\\opt.rs","byte_start":1245,"byte_end":1251,"line_start":6,"line_end":6,"column_start":15,"column_end":21},"ref_id":{"krate":5,"index":5079}},{"kind":"Type","span":{"file_name":"src\\opt.rs","byte_start":1310,"byte_end":1316,"line_start":8,"line_end":8,"column_start":21,"column_end":27},"ref_id":{"krate":5,"index":5079}},{"kind":"Type","span":{"file_name":"src\\opt.rs","byte_start":1387,"byte_end":1393,"line_start":10,"line_end":10,"column_start":21,"column_end":27},"ref_id":{"krate":5,"index":5079}},{"kind":"Type","span":{"file_name":"src\\opt.rs","byte_start":1469,"byte_end":1475,"line_start":12,"line_end":12,"column_start":16,"column_end":22},"ref_id":{"krate":2,"index":30242}},{"kind":"Type","span":{"file_name":"src\\opt.rs","byte_start":1476,"byte_end":1482,"line_start":12,"line_end":12,"column_start":23,"column_end":29},"ref_id":{"krate":5,"index":5079}},{"kind":"Type","span":{"file_name":"src\\opt.rs","byte_start":1190,"byte_end":1193,"line_start":4,"line_end":4,"column_start":13,"column_end":16},"ref_id":{"krate":0,"index":45}},{"kind":"Variable","span":{"file_name":"src\\opt.rs","byte_start":1239,"byte_end":1244,"line_start":6,"line_end":6,"column_start":9,"column_end":14},"ref_id":{"krate":0,"index":46}},{"kind":"Variable","span":{"file_name":"src\\opt.rs","byte_start":1298,"byte_end":1309,"line_start":8,"line_end":8,"column_start":9,"column_end":20},"ref_id":{"krate":0,"index":47}},{"kind":"Variable","span":{"file_name":"src\\opt.rs","byte_start":1375,"byte_end":1386,"line_start":10,"line_end":10,"column_start":9,"column_end":20},"ref_id":{"krate":0,"index":48}},{"kind":"Variable","span":{"file_name":"src\\opt.rs","byte_start":1462,"byte_end":1468,"line_start":12,"line_end":12,"column_start":9,"column_end":15},"ref_id":{"krate":0,"index":49}},{"kind":"Type","span":{"file_name":"src\\opt.rs","byte_start":1190,"byte_end":1193,"line_start":4,"line_end":4,"column_start":13,"column_end":16},"ref_id":{"krate":0,"index":45}},{"kind":"Type","span":{"file_name":"src\\opt.rs","byte_start":1245,"byte_end":1251,"line_start":6,"line_end":6,"column_start":15,"column_end":21},"ref_id":{"krate":5,"index":5079}},{"kind":"Type","span":{"file_name":"src\\opt.rs","byte_start":1310,"byte_end":1316,"line_start":8,"line_end":8,"column_start":21,"column_end":27},"ref_id":{"krate":5,"index":5079}},{"kind":"Type","span":{"file_name":"src\\opt.rs","byte_start":1387,"byte_end":1393,"line_start":10,"line_end":10,"column_start":21,"column_end":27},"ref_id":{"krate":5,"index":5079}},{"kind":"Type","span":{"file_name":"src\\opt.rs","byte_start":1476,"byte_end":1482,"line_start":12,"line_end":12,"column_start":23,"column_end":29},"ref_id":{"krate":5,"index":5079}},{"kind":"Variable","span":{"file_name":"src\\opt.rs","byte_start":1239,"byte_end":1244,"line_start":6,"line_end":6,"column_start":9,"column_end":14},"ref_id":{"krate":0,"index":46}},{"kind":"Variable","span":{"file_name":"src\\opt.rs","byte_start":1298,"byte_end":1309,"line_start":8,"line_end":8,"column_start":9,"column_end":20},"ref_id":{"krate":0,"index":47}},{"kind":"Variable","span":{"file_name":"src\\opt.rs","byte_start":1375,"byte_end":1386,"line_start":10,"line_end":10,"column_start":9,"column_end":20},"ref_id":{"krate":0,"index":48}},{"kind":"Variable","span":{"file_name":"src\\opt.rs","byte_start":1462,"byte_end":1468,"line_start":12,"line_end":12,"column_start":9,"column_end":15},"ref_id":{"krate":0,"index":49}},{"kind":"Mod","span":{"file_name":"src\\main.rs","byte_start":39,"byte_end":42,"line_start":3,"line_end":3,"column_start":5,"column_end":8},"ref_id":{"krate":0,"index":4}},{"kind":"Mod","span":{"file_name":"src\\main.rs","byte_start":53,"byte_end":56,"line_start":4,"line_end":4,"column_start":5,"column_end":8},"ref_id":{"krate":0,"index":7}},{"kind":"Mod","span":{"file_name":"src\\err.rs","byte_start":1503,"byte_end":1506,"line_start":1,"line_end":1,"column_start":5,"column_end":8},"ref_id":{"krate":1,"index":0}},{"kind":"Type","span":{"file_name":"src\\err.rs","byte_start":1556,"byte_end":1561,"line_start":4,"line_end":4,"column_start":12,"column_end":17},"ref_id":{"krate":1,"index":2591}},{"kind":"Mod","span":{"file_name":"src\\err.rs","byte_start":1552,"byte_end":1554,"line_start":4,"line_end":4,"column_start":8,"column_end":10},"ref_id":{"krate":1,"index":2354}},{"kind":"Type","span":{"file_name":"src\\err.rs","byte_start":1619,"byte_end":1624,"line_start":8,"line_end":8,"column_start":26,"column_end":31},"ref_id":{"krate":0,"index":78}},{"kind":"Type","span":{"file_name":"src\\err.rs","byte_start":1599,"byte_end":1603,"line_start":8,"line_end":8,"column_start":6,"column_end":10},"ref_id":{"krate":2,"index":1889}},{"kind":"Type","span":{"file_name":"src\\err.rs","byte_start":1608,"byte_end":1613,"line_start":8,"line_end":8,"column_start":15,"column_end":20},"ref_id":{"krate":1,"index":2591}},{"kind":"Mod","span":{"file_name":"src\\err.rs","byte_start":1604,"byte_end":1606,"line_start":8,"line_end":8,"column_start":11,"column_end":13},"ref_id":{"krate":1,"index":2354}},{"kind":"Type","span":{"file_name":"src\\err.rs","byte_start":1644,"byte_end":1649,"line_start":9,"line_end":9,"column_start":19,"column_end":24},"ref_id":{"krate":1,"index":2591}},{"kind":"Mod","span":{"file_name":"src\\err.rs","byte_start":1640,"byte_end":1642,"line_start":9,"line_end":9,"column_start":15,"column_end":17},"ref_id":{"krate":1,"index":2354}},{"kind":"Type","span":{"file_name":"src\\err.rs","byte_start":1652,"byte_end":1657,"line_start":9,"line_end":9,"column_start":27,"column_end":32},"ref_id":{"krate":0,"index":78}},{"kind":"Type","span":{"file_name":"src\\err.rs","byte_start":1674,"byte_end":1676,"line_start":10,"line_end":10,"column_start":16,"column_end":18},"ref_id":{"krate":0,"index":79}},{"kind":"Type","span":{"file_name":"src\\err.rs","byte_start":1667,"byte_end":1672,"line_start":10,"line_end":10,"column_start":9,"column_end":14},"ref_id":{"krate":0,"index":78}},{"kind":"Variable","span":{"file_name":"src\\err.rs","byte_start":1677,"byte_end":1678,"line_start":10,"line_end":10,"column_start":19,"column_end":20},"ref_id":{"krate":0,"index":2147483658}},{"kind":"Type","span":{"file_name":"src\\err.rs","byte_start":1716,"byte_end":1721,"line_start":13,"line_end":13,"column_start":29,"column_end":34},"ref_id":{"krate":0,"index":78}},{"kind":"Type","span":{"file_name":"src\\err.rs","byte_start":1693,"byte_end":1697,"line_start":13,"line_end":13,"column_start":6,"column_end":10},"ref_id":{"krate":2,"index":1889}},{"kind":"Type","span":{"file_name":"src\\err.rs","byte_start":1752,"byte_end":1757,"line_start":14,"line_end":14,"column_start":30,"column_end":35},"ref_id":{"krate":0,"index":78}},{"kind":"Type","span":{"file_name":"src\\err.rs","byte_start":1774,"byte_end":1781,"line_start":15,"line_end":15,"column_start":16,"column_end":23},"ref_id":{"krate":0,"index":82}},{"kind":"Type","span":{"file_name":"src\\err.rs","byte_start":1767,"byte_end":1772,"line_start":15,"line_end":15,"column_start":9,"column_end":14},"ref_id":{"krate":0,"index":78}},{"kind":"Variable","span":{"file_name":"src\\err.rs","byte_start":1782,"byte_end":1783,"line_start":15,"line_end":15,"column_start":24,"column_end":25},"ref_id":{"krate":0,"index":2147483660}},{"kind":"Mod","span":{"file_name":"src\\main.rs","byte_start":62,"byte_end":66,"line_start":5,"line_end":5,"column_start":5,"column_end":9},"ref_id":{"krate":0,"index":13}},{"kind":"Mod","span":{"file_name":"src\\core.rs","byte_start":1817,"byte_end":1821,"line_start":1,"line_end":1,"column_start":9,"column_end":13},"ref_id":{"krate":0,"index":14}},{"kind":"Type","span":{"file_name":"src\\core\\read.rs","byte_start":2035,"byte_end":2040,"line_start":7,"line_end":7,"column_start":5,"column_end":10},"ref_id":{"krate":0,"index":78}},{"kind":"Type","span":{"file_name":"src\\core\\read.rs","byte_start":2035,"byte_end":2040,"line_start":7,"line_end":7,"column_start":5,"column_end":10},"ref_id":{"krate":1,"index":7320}},{"kind":"Type","span":{"file_name":"src\\core\\read.rs","byte_start":2035,"byte_end":2040,"line_start":7,"line_end":7,"column_start":5,"column_end":10},"ref_id":{"krate":1,"index":2193}},{"kind":"Type","span":{"file_name":"src\\core\\read.rs","byte_start":2035,"byte_end":2040,"line_start":7,"line_end":7,"column_start":5,"column_end":10},"ref_id":{"krate":1,"index":2993}},{"kind":"Type","span":{"file_name":"src\\core\\read.rs","byte_start":2035,"byte_end":2040,"line_start":7,"line_end":7,"column_start":5,"column_end":10},"ref_id":{"krate":1,"index":3052}},{"kind":"Type","span":{"file_name":"src\\core\\read.rs","byte_start":2100,"byte_end":2107,"line_start":8,"line_end":8,"column_start":26,"column_end":33},"ref_id":{"krate":1,"index":7320}},{"kind":"Type","span":{"file_name":"src\\core\\read.rs","byte_start":2110,"byte_end":2116,"line_start":8,"line_end":8,"column_start":36,"column_end":42},"ref_id":{"krate":2,"index":30401}},{"kind":"Type","span":{"file_name":"src\\core\\read.rs","byte_start":2117,"byte_end":2123,"line_start":8,"line_end":8,"column_start":43,"column_end":49},"ref_id":{"krate":5,"index":5079}},{"kind":"Type","span":{"file_name":"src\\core\\read.rs","byte_start":2124,"byte_end":2129,"line_start":8,"line_end":8,"column_start":50,"column_end":55},"ref_id":{"krate":0,"index":78}},{"kind":"Function","span":{"file_name":"src\\core\\read.rs","byte_start":2145,"byte_end":2149,"line_start":9,"line_end":9,"column_start":14,"column_end":18},"ref_id":{"krate":0,"index":23}},{"kind":"Variable","span":{"file_name":"src\\core\\read.rs","byte_start":2150,"byte_end":2158,"line_start":9,"line_end":9,"column_start":19,"column_end":27},"ref_id":{"krate":0,"index":2147483669}},{"kind":"Variable","span":{"file_name":"src\\core\\read.rs","byte_start":2145,"byte_end":2160,"line_start":9,"line_end":9,"column_start":14,"column_end":29},"ref_id":{"krate":2,"index":30406}},{"kind":"Type","span":{"file_name":"src\\core\\read.rs","byte_start":2166,"byte_end":2168,"line_start":10,"line_end":10,"column_start":5,"column_end":7},"ref_id":{"krate":2,"index":30404}},{"kind":"Variable","span":{"file_name":"src\\core\\read.rs","byte_start":2169,"byte_end":2173,"line_start":10,"line_end":10,"column_start":8,"column_end":12},"ref_id":{"krate":0,"index":1073741845}},{"kind":"Type","span":{"file_name":"src\\core\\read.rs","byte_start":2225,"byte_end":2231,"line_start":13,"line_end":13,"column_start":48,"column_end":54},"ref_id":{"krate":2,"index":30401}},{"kind":"Type","span":{"file_name":"src\\core\\read.rs","byte_start":2235,"byte_end":2240,"line_start":13,"line_end":13,"column_start":58,"column_end":63},"ref_id":{"krate":0,"index":78}},{"kind":"Function","span":{"file_name":"src\\core\\read.rs","byte_start":2247,"byte_end":2252,"line_start":14,"line_end":14,"column_start":5,"column_end":10},"ref_id":{"krate":0,"index":25}},{"kind":"Variable","span":{"file_name":"src\\core\\read.rs","byte_start":2253,"byte_end":2261,"line_start":14,"line_end":14,"column_start":11,"column_end":19},"ref_id":{"krate":0,"index":2147483670}},{"kind":"Variable","span":{"file_name":"src\\core\\read.rs","byte_start":2262,"byte_end":2270,"line_start":14,"line_end":14,"column_start":20,"column_end":28},"ref_id":{"krate":0,"index":1073741846}},{"kind":"Variable","span":{"file_name":"src\\core\\read.rs","byte_start":2247,"byte_end":2272,"line_start":14,"line_end":14,"column_start":5,"column_end":30},"ref_id":{"krate":2,"index":30406}},{"kind":"Type","span":{"file_name":"src\\core\\read.rs","byte_start":2278,"byte_end":2280,"line_start":15,"line_end":15,"column_start":5,"column_end":7},"ref_id":{"krate":2,"index":30404}},{"kind":"Type","span":{"file_name":"src\\core\\read.rs","byte_start":2301,"byte_end":2308,"line_start":18,"line_end":18,"column_start":14,"column_end":21},"ref_id":{"krate":1,"index":7320}},{"kind":"Type","span":{"file_name":"src\\core\\read.rs","byte_start":2311,"byte_end":2317,"line_start":18,"line_end":18,"column_start":24,"column_end":30},"ref_id":{"krate":2,"index":30401}},{"kind":"Type","span":{"file_name":"src\\core\\read.rs","byte_start":2318,"byte_end":2324,"line_start":18,"line_end":18,"column_start":31,"column_end":37},"ref_id":{"krate":5,"index":5079}},{"kind":"Type","span":{"file_name":"src\\core\\read.rs","byte_start":2325,"byte_end":2330,"line_start":18,"line_end":18,"column_start":38,"column_end":43},"ref_id":{"krate":0,"index":78}},{"kind":"Function","span":{"file_name":"src\\core\\read.rs","byte_start":2360,"byte_end":2363,"line_start":19,"line_end":19,"column_start":28,"column_end":31},"ref_id":{"krate":5,"index":3718}},{"kind":"Type","span":{"file_name":"src\\core\\read.rs","byte_start":2352,"byte_end":2358,"line_start":19,"line_end":19,"column_start":20,"column_end":26},"ref_id":{"krate":5,"index":5079}},{"kind":"Function","span":{"file_name":"src\\core\\read.rs","byte_start":2384,"byte_end":2388,"line_start":20,"line_end":20,"column_start":18,"column_end":22},"ref_id":{"krate":0,"index":24}},{"kind":"Variable","span":{"file_name":"src\\core\\read.rs","byte_start":2389,"byte_end":2393,"line_start":20,"line_end":20,"column_start":23,"column_end":27},"ref_id":{"krate":0,"index":2147483671}},{"kind":"Variable","span":{"file_name":"src\\core\\read.rs","byte_start":2384,"byte_end":2395,"line_start":20,"line_end":20,"column_start":18,"column_end":29},"ref_id":{"krate":2,"index":30406}},{"kind":"Function","span":{"file_name":"src\\core\\read.rs","byte_start":2406,"byte_end":2420,"line_start":21,"line_end":21,"column_start":10,"column_end":24},"ref_id":{"krate":1,"index":3000}},{"kind":"Variable","span":{"file_name":"src\\core\\read.rs","byte_start":2401,"byte_end":2405,"line_start":21,"line_end":21,"column_start":5,"column_end":9},"ref_id":{"krate":0,"index":3221225495}},{"kind":"Variable","span":{"file_name":"src\\core\\read.rs","byte_start":2426,"byte_end":2432,"line_start":21,"line_end":21,"column_start":30,"column_end":36},"ref_id":{"krate":0,"index":1073741847}},{"kind":"Variable","span":{"file_name":"src\\core\\read.rs","byte_start":2401,"byte_end":2434,"line_start":21,"line_end":21,"column_start":5,"column_end":38},"ref_id":{"krate":2,"index":30406}},{"kind":"Function","span":{"file_name":"src\\core\\read.rs","byte_start":2450,"byte_end":2458,"line_start":22,"line_end":22,"column_start":15,"column_end":23},"ref_id":{"krate":5,"index":3754}},{"kind":"Variable","span":{"file_name":"src\\core\\read.rs","byte_start":2443,"byte_end":2449,"line_start":22,"line_end":22,"column_start":8,"column_end":14},"ref_id":{"krate":0,"index":1073741847}},{"kind":"Type","span":{"file_name":"src\\core\\read.rs","byte_start":2477,"byte_end":2480,"line_start":23,"line_end":23,"column_start":16,"column_end":19},"ref_id":{"krate":2,"index":30407}},{"kind":"Variable","span":{"file_name":"src\\core\\read.rs","byte_start":2477,"byte_end":2503,"line_start":23,"line_end":23,"column_start":16,"column_end":42},"ref_id":{"krate":2,"index":30406}},{"kind":"Type","span":{"file_name":"src\\core\\read.rs","byte_start":2514,"byte_end":2516,"line_start":25,"line_end":25,"column_start":5,"column_end":7},"ref_id":{"krate":2,"index":30404}},{"kind":"Variable","span":{"file_name":"src\\core\\read.rs","byte_start":2517,"byte_end":2523,"line_start":25,"line_end":25,"column_start":8,"column_end":14},"ref_id":{"krate":0,"index":1073741847}},{"kind":"Type","span":{"file_name":"src\\core\\read.rs","byte_start":2540,"byte_end":2547,"line_start":27,"line_end":27,"column_start":14,"column_end":21},"ref_id":{"krate":1,"index":7320}},{"kind":"Type","span":{"file_name":"src\\core\\read.rs","byte_start":2550,"byte_end":2556,"line_start":27,"line_end":27,"column_start":24,"column_end":30},"ref_id":{"krate":2,"index":30401}},{"kind":"Type","span":{"file_name":"src\\core\\read.rs","byte_start":2557,"byte_end":2561,"line_start":27,"line_end":27,"column_start":31,"column_end":35},"ref_id":{"krate":1,"index":2193}},{"kind":"Type","span":{"file_name":"src\\core\\read.rs","byte_start":2562,"byte_end":2567,"line_start":27,"line_end":27,"column_start":36,"column_end":41},"ref_id":{"krate":0,"index":78}},{"kind":"Function","span":{"file_name":"src\\core\\read.rs","byte_start":2589,"byte_end":2593,"line_start":28,"line_end":28,"column_start":20,"column_end":24},"ref_id":{"krate":1,"index":2211}},{"kind":"Type","span":{"file_name":"src\\core\\read.rs","byte_start":2583,"byte_end":2587,"line_start":28,"line_end":28,"column_start":14,"column_end":18},"ref_id":{"krate":1,"index":2193}},{"kind":"Variable","span":{"file_name":"src\\core\\read.rs","byte_start":2594,"byte_end":2598,"line_start":28,"line_end":28,"column_start":25,"column_end":29},"ref_id":{"krate":0,"index":2147483672}},{"kind":"Variable","span":{"file_name":"src\\core\\read.rs","byte_start":2583,"byte_end":2600,"line_start":28,"line_end":28,"column_start":14,"column_end":31},"ref_id":{"krate":2,"index":30406}},{"kind":"Type","span":{"file_name":"src\\core\\read.rs","byte_start":2606,"byte_end":2608,"line_start":29,"line_end":29,"column_start":5,"column_end":7},"ref_id":{"krate":2,"index":30404}},{"kind":"Variable","span":{"file_name":"src\\core\\read.rs","byte_start":2609,"byte_end":2613,"line_start":29,"line_end":29,"column_start":8,"column_end":12},"ref_id":{"krate":0,"index":1073741848}},{"kind":"Type","span":{"file_name":"src\\core\\read.rs","byte_start":2652,"byte_end":2658,"line_start":31,"line_end":31,"column_start":36,"column_end":42},"ref_id":{"krate":2,"index":30401}},{"kind":"Type","span":{"file_name":"src\\core\\read.rs","byte_start":2662,"byte_end":2667,"line_start":31,"line_end":31,"column_start":46,"column_end":51},"ref_id":{"krate":0,"index":78}},{"kind":"Function","span":{"file_name":"src\\core\\read.rs","byte_start":2695,"byte_end":2701,"line_start":32,"line_end":32,"column_start":26,"column_end":32},"ref_id":{"krate":1,"index":2213}},{"kind":"Type","span":{"file_name":"src\\core\\read.rs","byte_start":2689,"byte_end":2693,"line_start":32,"line_end":32,"column_start":20,"column_end":24},"ref_id":{"krate":1,"index":2193}},{"kind":"Variable","span":{"file_name":"src\\core\\read.rs","byte_start":2702,"byte_end":2710,"line_start":32,"line_end":32,"column_start":33,"column_end":41},"ref_id":{"krate":0,"index":1073741849}},{"kind":"Variable","span":{"file_name":"src\\core\\read.rs","byte_start":2689,"byte_end":2712,"line_start":32,"line_end":32,"column_start":20,"column_end":43},"ref_id":{"krate":2,"index":30406}},{"kind":"Function","span":{"file_name":"src\\core\\read.rs","byte_start":2725,"byte_end":2734,"line_start":33,"line_end":33,"column_start":12,"column_end":21},"ref_id":{"krate":1,"index":3058}},{"kind":"Variable","span":{"file_name":"src\\core\\read.rs","byte_start":2718,"byte_end":2724,"line_start":33,"line_end":33,"column_start":5,"column_end":11},"ref_id":{"krate":0,"index":3221225497}},{"kind":"Function","span":{"file_name":"src\\core\\read.rs","byte_start":2740,"byte_end":2748,"line_start":33,"line_end":33,"column_start":27,"column_end":35},"ref_id":{"krate":2,"index":8172}},{"kind":"Variable","span":{"file_name":"src\\core\\read.rs","byte_start":2735,"byte_end":2739,"line_start":33,"line_end":33,"column_start":22,"column_end":26},"ref_id":{"krate":0,"index":2147483673}},{"kind":"Variable","span":{"file_name":"src\\core\\read.rs","byte_start":2718,"byte_end":2752,"line_start":33,"line_end":33,"column_start":5,"column_end":39},"ref_id":{"krate":2,"index":30406}},{"kind":"Type","span":{"file_name":"src\\core\\read.rs","byte_start":2758,"byte_end":2760,"line_start":34,"line_end":34,"column_start":5,"column_end":7},"ref_id":{"krate":2,"index":30404}},{"kind":"Mod","span":{"file_name":"src\\core.rs","byte_start":1831,"byte_end":1836,"line_start":2,"line_end":2,"column_start":9,"column_end":14},"ref_id":{"krate":0,"index":26}},{"kind":"Mod","span":{"file_name":"src\\core\\write.rs","byte_start":2805,"byte_end":2810,"line_start":1,"line_end":1,"column_start":5,"column_end":10},"ref_id":{"krate":0,"index":13}},{"kind":"Type","span":{"file_name":"src\\core\\write.rs","byte_start":2842,"byte_end":2848,"line_start":2,"line_end":2,"column_start":28,"column_end":34},"ref_id":{"krate":5,"index":5079}},{"kind":"Type","span":{"file_name":"src\\core\\write.rs","byte_start":2880,"byte_end":2886,"line_start":2,"line_end":2,"column_start":66,"column_end":72},"ref_id":{"krate":2,"index":30401}},{"kind":"Type","span":{"file_name":"src\\core\\write.rs","byte_start":2887,"byte_end":2893,"line_start":2,"line_end":2,"column_start":73,"column_end":79},"ref_id":{"krate":5,"index":5079}},{"kind":"Type","span":{"file_name":"src\\core\\write.rs","byte_start":2894,"byte_end":2899,"line_start":2,"line_end":2,"column_start":80,"column_end":85},"ref_id":{"krate":0,"index":78}},{"kind":"Function","span":{"file_name":"src\\core\\write.rs","byte_start":2925,"byte_end":2930,"line_start":3,"line_end":3,"column_start":24,"column_end":29},"ref_id":{"krate":2,"index":8193}},{"kind":"Variable","span":{"file_name":"src\\core\\write.rs","byte_start":2920,"byte_end":2924,"line_start":3,"line_end":3,"column_start":19,"column_end":23},"ref_id":{"krate":0,"index":2147483676}},{"kind":"Function","span":{"file_name":"src\\core\\write.rs","byte_start":2963,"byte_end":2969,"line_start":4,"line_end":4,"column_start":30,"column_end":36},"ref_id":{"krate":2,"index":5438}},{"kind":"Function","span":{"file_name":"src\\core\\write.rs","byte_start":2956,"byte_end":2960,"line_start":4,"line_end":4,"column_start":23,"column_end":27},"ref_id":{"krate":2,"index":5049}},{"kind":"Variable","span":{"file_name":"src\\core\\write.rs","byte_start":2950,"byte_end":2955,"line_start":4,"line_end":4,"column_start":17,"column_end":22},"ref_id":{"krate":0,"index":536870940}},{"kind":"Type","span":{"file_name":"src\\core\\write.rs","byte_start":2989,"byte_end":2992,"line_start":5,"line_end":5,"column_start":17,"column_end":20},"ref_id":{"krate":5,"index":4366}},{"kind":"Function","span":{"file_name":"src\\core\\write.rs","byte_start":3018,"byte_end":3025,"line_start":5,"line_end":5,"column_start":46,"column_end":53},"ref_id":{"krate":2,"index":5101}},{"kind":"Function","span":{"file_name":"src\\core\\write.rs","byte_start":3007,"byte_end":3012,"line_start":5,"line_end":5,"column_start":35,"column_end":40},"ref_id":{"krate":2,"index":8213}},{"kind":"Variable","span":{"file_name":"src\\core\\write.rs","byte_start":2999,"byte_end":3006,"line_start":5,"line_end":5,"column_start":27,"column_end":34},"ref_id":{"krate":0,"index":2684354588}},{"kind":"Function","span":{"file_name":"src\\core\\write.rs","byte_start":3066,"byte_end":3074,"line_start":6,"line_end":6,"column_start":38,"column_end":46},"ref_id":{"krate":2,"index":5187}},{"kind":"Function","span":{"file_name":"src\\core\\write.rs","byte_start":3059,"byte_end":3063,"line_start":6,"line_end":6,"column_start":31,"column_end":35},"ref_id":{"krate":2,"index":6783}},{"kind":"Variable","span":{"file_name":"src\\core\\write.rs","byte_start":3051,"byte_end":3058,"line_start":6,"line_end":6,"column_start":23,"column_end":30},"ref_id":{"krate":0,"index":1610612764}},{"kind":"Variable","span":{"file_name":"src\\core\\write.rs","byte_start":3080,"byte_end":3081,"line_start":6,"line_end":6,"column_start":52,"column_end":53},"ref_id":{"krate":0,"index":2415919132}},{"kind":"Variable","span":{"file_name":"src\\core\\write.rs","byte_start":3083,"byte_end":3089,"line_start":6,"line_end":6,"column_start":55,"column_end":61},"ref_id":{"krate":0,"index":1073741852}},{"kind":"Variable","span":{"file_name":"src\\core\\write.rs","byte_start":3120,"byte_end":3133,"line_start":7,"line_end":7,"column_start":29,"column_end":42},"ref_id":{"krate":0,"index":3758096412}},{"kind":"Type","span":{"file_name":"src\\core\\write.rs","byte_start":3143,"byte_end":3147,"line_start":8,"line_end":8,"column_start":9,"column_end":13},"ref_id":{"krate":2,"index":30246}},{"kind":"Type","span":{"file_name":"src\\core\\write.rs","byte_start":3143,"byte_end":3147,"line_start":8,"line_end":8,"column_start":9,"column_end":13},"ref_id":{"krate":2,"index":30246}},{"kind":"Variable","span":{"file_name":"src\\core\\write.rs","byte_start":3157,"byte_end":3163,"line_start":8,"line_end":8,"column_start":23,"column_end":29},"ref_id":{"krate":0,"index":805306396}},{"kind":"Type","span":{"file_name":"src\\core\\write.rs","byte_start":3173,"byte_end":3177,"line_start":9,"line_end":9,"column_start":9,"column_end":13},"ref_id":{"krate":2,"index":30244}},{"kind":"Type","span":{"file_name":"src\\core\\write.rs","byte_start":3173,"byte_end":3177,"line_start":9,"line_end":9,"column_start":9,"column_end":13},"ref_id":{"krate":2,"index":30244}},{"kind":"Type","span":{"file_name":"src\\core\\write.rs","byte_start":3179,"byte_end":3182,"line_start":9,"line_end":9,"column_start":15,"column_end":18},"ref_id":{"krate":2,"index":30407}},{"kind":"Variable","span":{"file_name":"src\\core\\write.rs","byte_start":3179,"byte_end":3229,"line_start":9,"line_end":9,"column_start":15,"column_end":65},"ref_id":{"krate":2,"index":30406}},{"kind":"Function","span":{"file_name":"src\\core\\write.rs","byte_start":3264,"byte_end":3277,"line_start":11,"line_end":11,"column_start":28,"column_end":41},"ref_id":{"krate":5,"index":3719}},{"kind":"Type","span":{"file_name":"src\\core\\write.rs","byte_start":3256,"byte_end":3262,"line_start":11,"line_end":11,"column_start":20,"column_end":26},"ref_id":{"krate":5,"index":5079}},{"kind":"Function","span":{"file_name":"src\\core\\write.rs","byte_start":3283,"byte_end":3291,"line_start":11,"line_end":11,"column_start":47,"column_end":55},"ref_id":{"krate":5,"index":3733}},{"kind":"Variable","span":{"file_name":"src\\core\\write.rs","byte_start":3278,"byte_end":3282,"line_start":11,"line_end":11,"column_start":42,"column_end":46},"ref_id":{"krate":0,"index":2147483676}},{"kind":"Function","span":{"file_name":"src\\core\\write.rs","byte_start":3307,"byte_end":3315,"line_start":12,"line_end":12,"column_start":12,"column_end":20},"ref_id":{"krate":5,"index":3732}},{"kind":"Variable","span":{"file_name":"src\\core\\write.rs","byte_start":3300,"byte_end":3306,"line_start":12,"line_end":12,"column_start":5,"column_end":11},"ref_id":{"krate":0,"index":1879048220}},{"kind":"Function","span":{"file_name":"src\\core\\write.rs","byte_start":3325,"byte_end":3329,"line_start":12,"line_end":12,"column_start":30,"column_end":34},"ref_id":{"krate":5,"index":3500}},{"kind":"Variable","span":{"file_name":"src\\core\\write.rs","byte_start":3317,"byte_end":3324,"line_start":12,"line_end":12,"column_start":22,"column_end":29},"ref_id":{"krate":0,"index":1610612764}},{"kind":"Function","span":{"file_name":"src\\core\\write.rs","byte_start":3348,"byte_end":3352,"line_start":13,"line_end":13,"column_start":12,"column_end":16},"ref_id":{"krate":5,"index":3740}},{"kind":"Variable","span":{"file_name":"src\\core\\write.rs","byte_start":3341,"byte_end":3347,"line_start":13,"line_end":13,"column_start":5,"column_end":11},"ref_id":{"krate":0,"index":1879048220}},{"kind":"Variable","span":{"file_name":"src\\core\\write.rs","byte_start":3376,"byte_end":3381,"line_start":14,"line_end":14,"column_start":17,"column_end":22},"ref_id":{"krate":0,"index":536870940}},{"kind":"Variable","span":{"file_name":"src\\core\\write.rs","byte_start":3368,"byte_end":3372,"line_start":14,"line_end":14,"column_start":9,"column_end":13},"ref_id":{"krate":2,"index":30248}},{"kind":"Type","span":{"file_name":"src\\core\\write.rs","byte_start":3407,"byte_end":3410,"line_start":15,"line_end":15,"column_start":25,"column_end":28},"ref_id":{"krate":5,"index":4366}},{"kind":"Function","span":{"file_name":"src\\core\\write.rs","byte_start":3433,"byte_end":3440,"line_start":15,"line_end":15,"column_start":51,"column_end":58},"ref_id":{"krate":2,"index":5101}},{"kind":"Function","span":{"file_name":"src\\core\\write.rs","byte_start":3422,"byte_end":3427,"line_start":15,"line_end":15,"column_start":40,"column_end":45},"ref_id":{"krate":2,"index":8213}},{"kind":"Variable","span":{"file_name":"src\\core\\write.rs","byte_start":3417,"byte_end":3421,"line_start":15,"line_end":15,"column_start":35,"column_end":39},"ref_id":{"krate":0,"index":4026531868}},{"kind":"Variable","span":{"file_name":"src\\core\\write.rs","byte_start":3475,"byte_end":3486,"line_start":16,"line_end":16,"column_start":32,"column_end":43},"ref_id":{"krate":0,"index":3221225500}},{"kind":"Variable","span":{"file_name":"src\\core\\write.rs","byte_start":3452,"byte_end":3459,"line_start":16,"line_end":16,"column_start":9,"column_end":16},"ref_id":{"krate":0,"index":134217756}},{"kind":"Variable","span":{"file_name":"src\\core\\write.rs","byte_start":3460,"byte_end":3473,"line_start":16,"line_end":16,"column_start":17,"column_end":30},"ref_id":{"krate":0,"index":1342177308}},{"kind":"Function","span":{"file_name":"src\\core\\write.rs","byte_start":3503,"byte_end":3507,"line_start":17,"line_end":17,"column_start":16,"column_end":20},"ref_id":{"krate":5,"index":3740}},{"kind":"Variable","span":{"file_name":"src\\core\\write.rs","byte_start":3496,"byte_end":3502,"line_start":17,"line_end":17,"column_start":9,"column_end":15},"ref_id":{"krate":0,"index":1879048220}},{"kind":"Type","span":{"file_name":"src\\core\\write.rs","byte_start":3525,"byte_end":3527,"line_start":19,"line_end":19,"column_start":5,"column_end":7},"ref_id":{"krate":2,"index":30404}},{"kind":"Variable","span":{"file_name":"src\\core\\write.rs","byte_start":3528,"byte_end":3534,"line_start":19,"line_end":19,"column_start":8,"column_end":14},"ref_id":{"krate":0,"index":1879048220}},{"kind":"Type","span":{"file_name":"src\\core.rs","byte_start":1842,"byte_end":1847,"line_start":3,"line_end":3,"column_start":5,"column_end":10},"ref_id":{"krate":0,"index":78}},{"kind":"Mod","span":{"file_name":"src\\core.rs","byte_start":1849,"byte_end":1852,"line_start":3,"line_end":3,"column_start":12,"column_end":15},"ref_id":{"krate":0,"index":7}},{"kind":"Type","span":{"file_name":"src\\core.rs","byte_start":1865,"byte_end":1868,"line_start":4,"line_end":4,"column_start":5,"column_end":8},"ref_id":{"krate":1,"index":7320}},{"kind":"Mod","span":{"file_name":"src\\core.rs","byte_start":1876,"byte_end":1880,"line_start":5,"line_end":5,"column_start":5,"column_end":9},"ref_id":{"krate":1,"index":3876}},{"kind":"Type","span":{"file_name":"src\\core.rs","byte_start":1865,"byte_end":1868,"line_start":4,"line_end":4,"column_start":5,"column_end":8},"ref_id":{"krate":1,"index":2193}},{"kind":"Mod","span":{"file_name":"src\\core.rs","byte_start":1895,"byte_end":1897,"line_start":6,"line_end":6,"column_start":5,"column_end":7},"ref_id":{"krate":1,"index":2171}},{"kind":"Type","span":{"file_name":"src\\core.rs","byte_start":1865,"byte_end":1868,"line_start":4,"line_end":4,"column_start":5,"column_end":8},"ref_id":{"krate":1,"index":2993}},{"kind":"Type","span":{"file_name":"src\\core.rs","byte_start":1909,"byte_end":1911,"line_start":7,"line_end":7,"column_start":5,"column_end":7},"ref_id":{"krate":1,"index":2993}},{"kind":"Type","span":{"file_name":"src\\core.rs","byte_start":1865,"byte_end":1868,"line_start":4,"line_end":4,"column_start":5,"column_end":8},"ref_id":{"krate":1,"index":3052}},{"kind":"Type","span":{"file_name":"src\\core.rs","byte_start":1909,"byte_end":1911,"line_start":7,"line_end":7,"column_start":5,"column_end":7},"ref_id":{"krate":1,"index":3052}},{"kind":"Function","span":{"file_name":"src\\main.rs","byte_start":118,"byte_end":122,"line_start":7,"line_end":7,"column_start":5,"column_end":9},"ref_id":{"krate":0,"index":21}},{"kind":"Function","span":{"file_name":"src\\main.rs","byte_start":124,"byte_end":128,"line_start":7,"line_end":7,"column_start":11,"column_end":15},"ref_id":{"krate":0,"index":21}},{"kind":"Function","span":{"file_name":"src\\main.rs","byte_start":136,"byte_end":140,"line_start":8,"line_end":8,"column_start":5,"column_end":9},"ref_id":{"krate":0,"index":21}},{"kind":"Function","span":{"file_name":"src\\main.rs","byte_start":118,"byte_end":122,"line_start":7,"line_end":7,"column_start":5,"column_end":9},"ref_id":{"krate":0,"index":22}},{"kind":"Function","span":{"file_name":"src\\main.rs","byte_start":124,"byte_end":128,"line_start":7,"line_end":7,"column_start":11,"column_end":15},"ref_id":{"krate":0,"index":22}},{"kind":"Function","span":{"file_name":"src\\main.rs","byte_start":136,"byte_end":140,"line_start":8,"line_end":8,"column_start":5,"column_end":9},"ref_id":{"krate":0,"index":22}},{"kind":"Function","span":{"file_name":"src\\main.rs","byte_start":118,"byte_end":122,"line_start":7,"line_end":7,"column_start":5,"column_end":9},"ref_id":{"krate":0,"index":28}},{"kind":"Function","span":{"file_name":"src\\main.rs","byte_start":124,"byte_end":128,"line_start":7,"line_end":7,"column_start":11,"column_end":15},"ref_id":{"krate":0,"index":28}},{"kind":"Mod","span":{"file_name":"src\\main.rs","byte_start":168,"byte_end":173,"line_start":9,"line_end":9,"column_start":5,"column_end":10},"ref_id":{"krate":0,"index":26}},{"kind":"Mod","span":{"file_name":"src\\main.rs","byte_start":198,"byte_end":201,"line_start":11,"line_end":11,"column_start":5,"column_end":8},"ref_id":{"krate":1,"index":0}},{"kind":"Mod","span":{"file_name":"src\\main.rs","byte_start":203,"byte_end":207,"line_start":11,"line_end":11,"column_start":10,"column_end":14},"ref_id":{"krate":1,"index":3876}},{"kind":"Mod","span":{"file_name":"src\\main.rs","byte_start":222,"byte_end":225,"line_start":12,"line_end":12,"column_start":5,"column_end":8},"ref_id":{"krate":1,"index":0}},{"kind":"Function","span":{"file_name":"src\\main.rs","byte_start":265,"byte_end":274,"line_start":14,"line_end":14,"column_start":18,"column_end":27},"ref_id":{"krate":13,"index":14}},{"kind":"Type","span":{"file_name":"src\\main.rs","byte_start":260,"byte_end":263,"line_start":14,"line_end":14,"column_start":13,"column_end":16},"ref_id":{"krate":0,"index":45}},{"kind":"Function","span":{"file_name":"src\\main.rs","byte_start":304,"byte_end":308,"line_start":15,"line_end":15,"column_start":27,"column_end":31},"ref_id":{"krate":2,"index":1891}},{"kind":"Type","span":{"file_name":"src\\main.rs","byte_start":295,"byte_end":302,"line_start":15,"line_end":15,"column_start":18,"column_end":25},"ref_id":{"krate":1,"index":7320}},{"kind":"Variable","span":{"file_name":"src\\main.rs","byte_start":309,"byte_end":312,"line_start":15,"line_end":15,"column_start":32,"column_end":35},"ref_id":{"krate":0,"index":2147483692}},{"kind":"Variable","span":{"file_name":"src\\main.rs","byte_start":313,"byte_end":318,"line_start":15,"line_end":15,"column_start":36,"column_end":41},"ref_id":{"krate":0,"index":46}},{"kind":"Function","span":{"file_name":"src\\main.rs","byte_start":349,"byte_end":357,"line_start":17,"line_end":17,"column_start":24,"column_end":32},"ref_id":{"krate":0,"index":21}},{"kind":"Variable","span":{"file_name":"src\\main.rs","byte_start":358,"byte_end":366,"line_start":17,"line_end":17,"column_start":33,"column_end":41},"ref_id":{"krate":0,"index":1073741868}},{"kind":"Type","span":{"file_name":"src\\main.rs","byte_start":377,"byte_end":379,"line_start":18,"line_end":18,"column_start":9,"column_end":11},"ref_id":{"krate":2,"index":30404}},{"kind":"Type","span":{"file_name":"src\\main.rs","byte_start":377,"byte_end":379,"line_start":18,"line_end":18,"column_start":9,"column_end":11},"ref_id":{"krate":2,"index":30404}},{"kind":"Variable","span":{"file_name":"src\\main.rs","byte_start":389,"byte_end":394,"line_start":18,"line_end":18,"column_start":21,"column_end":26},"ref_id":{"krate":0,"index":2684354604}},{"kind":"Type","span":{"file_name":"src\\main.rs","byte_start":405,"byte_end":408,"line_start":19,"line_end":19,"column_start":9,"column_end":12},"ref_id":{"krate":2,"index":30407}},{"kind":"Type","span":{"file_name":"src\\main.rs","byte_start":405,"byte_end":408,"line_start":19,"line_end":19,"column_start":9,"column_end":12},"ref_id":{"krate":2,"index":30407}},{"kind":"Function","span":{"file_name":"C:\\Users\\Pan\\.rustup/toolchains/stable-x86_64-pc-windows-msvc\\lib/rustlib/src/rust\\library\\std\\src\\macros.rs","byte_start":26870,"byte_end":26903,"line_start":96,"line_end":96,"column_start":28,"column_end":61},"ref_id":{"krate":2,"index":6311}},{"kind":"Variable","span":{"file_name":"src\\main.rs","byte_start":454,"byte_end":455,"line_start":20,"line_end":20,"column_start":40,"column_end":41},"ref_id":{"krate":0,"index":3758096428}},{"kind":"Function","span":{"file_name":"C:\\Users\\Pan\\.rustup/toolchains/stable-x86_64-pc-windows-msvc\\lib/rustlib/src/rust\\library\\std\\src\\macros.rs","byte_start":26870,"byte_end":26903,"line_start":96,"line_end":96,"column_start":28,"column_end":61},"ref_id":{"krate":2,"index":6304}},{"kind":"Function","span":{"file_name":"src\\main.rs","byte_start":479,"byte_end":483,"line_start":21,"line_end":21,"column_start":22,"column_end":26},"ref_id":{"krate":1,"index":4394}},{"kind":"Mod","span":{"file_name":"src\\main.rs","byte_start":470,"byte_end":477,"line_start":21,"line_end":21,"column_start":13,"column_end":20},"ref_id":{"krate":1,"index":4237}},{"kind":"Function","span":{"file_name":"src\\main.rs","byte_start":533,"byte_end":547,"line_start":24,"line_end":24,"column_start":29,"column_end":43},"ref_id":{"krate":0,"index":28}},{"kind":"Variable","span":{"file_name":"src\\main.rs","byte_start":548,"byte_end":556,"line_start":24,"line_end":24,"column_start":44,"column_end":52},"ref_id":{"krate":0,"index":3221225516}},{"kind":"Variable","span":{"file_name":"src\\main.rs","byte_start":558,"byte_end":561,"line_start":24,"line_end":24,"column_start":54,"column_end":57},"ref_id":{"krate":0,"index":2147483692}},{"kind":"Variable","span":{"file_name":"src\\main.rs","byte_start":562,"byte_end":573,"line_start":24,"line_end":24,"column_start":58,"column_end":69},"ref_id":{"krate":0,"index":47}},{"kind":"Variable","span":{"file_name":"src\\main.rs","byte_start":575,"byte_end":578,"line_start":24,"line_end":24,"column_start":71,"column_end":74},"ref_id":{"krate":0,"index":2147483692}},{"kind":"Variable","span":{"file_name":"src\\main.rs","byte_start":579,"byte_end":590,"line_start":24,"line_end":24,"column_start":75,"column_end":86},"ref_id":{"krate":0,"index":48}},{"kind":"Type","span":{"file_name":"src\\main.rs","byte_start":601,"byte_end":603,"line_start":25,"line_end":25,"column_start":9,"column_end":11},"ref_id":{"krate":2,"index":30404}},{"kind":"Type","span":{"file_name":"src\\main.rs","byte_start":601,"byte_end":603,"line_start":25,"line_end":25,"column_start":9,"column_end":11},"ref_id":{"krate":2,"index":30404}},{"kind":"Variable","span":{"file_name":"src\\main.rs","byte_start":611,"byte_end":615,"line_start":25,"line_end":25,"column_start":19,"column_end":23},"ref_id":{"krate":0,"index":805306412}},{"kind":"Type","span":{"file_name":"src\\main.rs","byte_start":625,"byte_end":628,"line_start":26,"line_end":26,"column_start":9,"column_end":12},"ref_id":{"krate":2,"index":30407}},{"kind":"Type","span":{"file_name":"src\\main.rs","byte_start":625,"byte_end":628,"line_start":26,"line_end":26,"column_start":9,"column_end":12},"ref_id":{"krate":2,"index":30407}},{"kind":"Function","span":{"file_name":"C:\\Users\\Pan\\.rustup/toolchains/stable-x86_64-pc-windows-msvc\\lib/rustlib/src/rust\\library\\std\\src\\macros.rs","byte_start":26870,"byte_end":26903,"line_start":96,"line_end":96,"column_start":28,"column_end":61},"ref_id":{"krate":2,"index":6311}},{"kind":"Variable","span":{"file_name":"src\\main.rs","byte_start":674,"byte_end":675,"line_start":27,"line_end":27,"column_start":40,"column_end":41},"ref_id":{"krate":0,"index":1879048236}},{"kind":"Function","span":{"file_name":"C:\\Users\\Pan\\.rustup/toolchains/stable-x86_64-pc-windows-msvc\\lib/rustlib/src/rust\\library\\std\\src\\macros.rs","byte_start":26870,"byte_end":26903,"line_start":96,"line_end":96,"column_start":28,"column_end":61},"ref_id":{"krate":2,"index":6304}},{"kind":"Function","span":{"file_name":"src\\main.rs","byte_start":699,"byte_end":703,"line_start":28,"line_end":28,"column_start":22,"column_end":26},"ref_id":{"krate":1,"index":4394}},{"kind":"Mod","span":{"file_name":"src\\main.rs","byte_start":690,"byte_end":697,"line_start":28,"line_end":28,"column_start":13,"column_end":20},"ref_id":{"krate":1,"index":4237}},{"kind":"Function","span":{"file_name":"src\\main.rs","byte_start":757,"byte_end":766,"line_start":31,"line_end":31,"column_start":33,"column_end":42},"ref_id":{"krate":2,"index":5439}},{"kind":"Variable","span":{"file_name":"src\\main.rs","byte_start":746,"byte_end":749,"line_start":31,"line_end":31,"column_start":22,"column_end":25},"ref_id":{"krate":0,"index":2147483692}},{"kind":"Variable","span":{"file_name":"src\\main.rs","byte_start":750,"byte_end":756,"line_start":31,"line_end":31,"column_start":26,"column_end":32},"ref_id":{"krate":0,"index":49}},{"kind":"Function","span":{"file_name":"src\\main.rs","byte_start":787,"byte_end":796,"line_start":31,"line_end":31,"column_start":63,"column_end":72},"ref_id":{"krate":5,"index":3895}},{"kind":"Function","span":{"file_name":"src\\main.rs","byte_start":859,"byte_end":868,"line_start":33,"line_end":33,"column_start":11,"column_end":20},"ref_id":{"krate":0,"index":22}},{"kind":"Variable","span":{"file_name":"src\\main.rs","byte_start":870,"byte_end":883,"line_start":33,"line_end":33,"column_start":22,"column_end":35},"ref_id":{"krate":0,"index":1342177324}},{"kind":"Variable","span":{"file_name":"src\\main.rs","byte_start":885,"byte_end":896,"line_start":33,"line_end":33,"column_start":37,"column_end":48},"ref_id":{"krate":0,"index":2281701420}},{"kind":"Type","span":{"file_name":"src\\main.rs","byte_start":907,"byte_end":909,"line_start":34,"line_end":34,"column_start":9,"column_end":11},"ref_id":{"krate":2,"index":30404}},{"kind":"Type","span":{"file_name":"src\\main.rs","byte_start":907,"byte_end":909,"line_start":34,"line_end":34,"column_start":9,"column_end":11},"ref_id":{"krate":2,"index":30404}},{"kind":"Function","span":{"file_name":"C:\\Users\\Pan\\.rustup/toolchains/stable-x86_64-pc-windows-msvc\\lib/rustlib/src/rust\\library\\std\\src\\macros.rs","byte_start":26870,"byte_end":26903,"line_start":96,"line_end":96,"column_start":28,"column_end":61},"ref_id":{"krate":2,"index":6311}},{"kind":"Type","span":{"file_name":"src\\main.rs","byte_start":975,"byte_end":978,"line_start":37,"line_end":37,"column_start":9,"column_end":12},"ref_id":{"krate":2,"index":30407}},{"kind":"Type","span":{"file_name":"src\\main.rs","byte_start":975,"byte_end":978,"line_start":37,"line_end":37,"column_start":9,"column_end":12},"ref_id":{"krate":2,"index":30407}},{"kind":"Function","span":{"file_name":"C:\\Users\\Pan\\.rustup/toolchains/stable-x86_64-pc-windows-msvc\\lib/rustlib/src/rust\\library\\std\\src\\macros.rs","byte_start":26870,"byte_end":26903,"line_start":96,"line_end":96,"column_start":28,"column_end":61},"ref_id":{"krate":2,"index":6311}},{"kind":"Variable","span":{"file_name":"src\\main.rs","byte_start":1024,"byte_end":1025,"line_start":38,"line_end":38,"column_start":40,"column_end":41},"ref_id":{"krate":0,"index":1744830508}},{"kind":"Function","span":{"file_name":"C:\\Users\\Pan\\.rustup/toolchains/stable-x86_64-pc-windows-msvc\\lib/rustlib/src/rust\\library\\std\\src\\macros.rs","byte_start":26870,"byte_end":26903,"line_start":96,"line_end":96,"column_start":28,"column_end":61},"ref_id":{"krate":2,"index":6304}},{"kind":"Function","span":{"file_name":"src\\main.rs","byte_start":1049,"byte_end":1053,"line_start":39,"line_end":39,"column_start":22,"column_end":26},"ref_id":{"krate":1,"index":4394}},{"kind":"Mod","span":{"file_name":"src\\main.rs","byte_start":1040,"byte_end":1047,"line_start":39,"line_end":39,"column_start":13,"column_end":20},"ref_id":{"krate":1,"index":4237}}],"macro_refs":[],"relations":[{"span":{"file_name":"src\\err.rs","byte_start":1619,"byte_end":1624,"line_start":8,"line_end":8,"column_start":26,"column_end":31},"kind":{"Impl":{"id":2}},"from":{"krate":0,"index":78},"to":{"krate":2,"index":1889}},{"span":{"file_name":"src\\err.rs","byte_start":1716,"byte_end":1721,"line_start":13,"line_end":13,"column_start":29,"column_end":34},"kind":{"Impl":{"id":3}},"from":{"krate":0,"index":78},"to":{"krate":2,"index":1889}}]}